[
	{
		"code": 978,
		"buy": 29.35,
		"sell": 29.75,
		"time": 1586091001918
	},
	{
		"code": 978,
		"buy": 29,
		"sell": 29.3,
		"time": 1586172601352
	},
	{
		"code": 978,
		"buy": 29.25,
		"sell": 29.7,
		"time": 1586157604801
	},
	{
		"code": 978,
		"buy": 29.15,
		"sell": 29.5,
		"time": 1586160004201
	},
	{
		"code": 978,
		"buy": 29.05,
		"sell": 29.39,
		"time": 1586260800988
	},
	{
		"code": 978,
		"buy": 28.85,
		"sell": 29.22,
		"time": 1586179201031
	},
	{
		"code": 978,
		"buy": 29,
		"sell": 29.39,
		"time": 1586253601049
	},
	{
		"code": 978,
		"buy": 29.2,
		"sell": 29.55,
		"time": 1586158202216
	},
	{
		"code": 978,
		"buy": 28.8,
		"sell": 29.2,
		"time": 1586184601355
	},
	{
		"code": 978,
		"buy": 29,
		"sell": 29.35,
		"time": 1586331006216
	},
	{
		"code": 978,
		"buy": 28.8,
		"sell": 29.29,
		"time": 1586245201332
	},
	{
		"code": 978,
		"buy": 29.15,
		"sell": 29.45,
		"time": 1586167201361
	},
	{
		"code": 978,
		"buy": 28.9,
		"sell": 29.29,
		"time": 1586247001506
	},
	{
		"code": 978,
		"buy": 29.25,
		"sell": 29.55,
		"time": 1586771401173
	},
	{
		"code": 978,
		"buy": 29.3,
		"sell": 29.5,
		"time": 1587538201358
	},
	{
		"code": 978,
		"buy": 29,
		"sell": 29.3,
		"time": 1587628801829
	},
	{
		"code": 978,
		"buy": 28.9,
		"sell": 29.15,
		"time": 1588754401706
	},
	{
		"code": 978,
		"buy": 28.85,
		"sell": 29.1,
		"time": 1588761601437
	},
	{
		"code": 978,
		"buy": 29.4,
		"sell": 29.75,
		"time": 1587022201329
	},
	{
		"code": 978,
		"buy": 29.35,
		"sell": 29.6,
		"time": 1587024601638
	},
	{
		"code": 978,
		"buy": 29.1,
		"sell": 29.32,
		"time": 1587715202577
	},
	{
		"code": 978,
		"buy": 29.2,
		"sell": 29.45,
		"time": 1586775001324
	},
	{
		"code": 978,
		"buy": 29.45,
		"sell": 29.7,
		"time": 1586859601547
	},
	{
		"code": 978,
		"buy": 29.3,
		"sell": 29.53,
		"time": 1587977401406
	},
	{
		"code": 978,
		"buy": 29.3,
		"sell": 29.6,
		"time": 1586421001436
	},
	{
		"code": 978,
		"buy": 29.05,
		"sell": 29.45,
		"time": 1586336401608
	},
	{
		"code": 978,
		"buy": 29.4,
		"sell": 29.65,
		"time": 1586764201585
	},
	{
		"code": 978,
		"buy": 29.3,
		"sell": 29.55,
		"time": 1587028201050
	},
	{
		"code": 978,
		"buy": 29.25,
		"sell": 29.45,
		"time": 1587454801558
	},
	{
		"code": 978,
		"buy": 29.41,
		"sell": 29.77,
		"time": 1586509802351
	},
	{
		"code": 978,
		"buy": 29.1,
		"sell": 29.35,
		"time": 1588240801881
	},
	{
		"code": 978,
		"buy": 29.4,
		"sell": 29.72,
		"time": 1586527201577
	},
	{
		"code": 978,
		"buy": 29.32,
		"sell": 29.57,
		"time": 1587035401294
	},
	{
		"code": 978,
		"buy": 29.22,
		"sell": 29.5,
		"time": 1588579201591
	},
	{
		"code": 978,
		"buy": 29.2,
		"sell": 29.5,
		"time": 1586418001826
	},
	{
		"code": 978,
		"buy": 29.3,
		"sell": 29.59,
		"time": 1586853601359
	},
	{
		"code": 978,
		"buy": 29.47,
		"sell": 29.77,
		"time": 1586876401100
	},
	{
		"code": 978,
		"buy": 29.6,
		"sell": 29.89,
		"time": 1586937001302
	},
	{
		"code": 978,
		"buy": 29.35,
		"sell": 29.54,
		"time": 1587543001572
	},
	{
		"code": 978,
		"buy": 29.15,
		"sell": 29.35,
		"time": 1587643201710
	},
	{
		"code": 978,
		"buy": 29.3,
		"sell": 29.5,
		"time": 1587984601385
	},
	{
		"code": 978,
		"buy": 29.25,
		"sell": 29.5,
		"time": 1586850601882
	},
	{
		"code": 978,
		"buy": 29.15,
		"sell": 29.35,
		"time": 1587109801558
	},
	{
		"code": 978,
		"buy": 29.25,
		"sell": 29.45,
		"time": 1587127801681
	},
	{
		"code": 978,
		"buy": 29.1,
		"sell": 29.35,
		"time": 1587624601785
	},
	{
		"code": 978,
		"buy": 28.92,
		"sell": 29.2,
		"time": 1588923601819
	},
	{
		"code": 978,
		"buy": 28.94,
		"sell": 29.2,
		"time": 1588930801710
	},
	{
		"code": 978,
		"buy": 29.35,
		"sell": 29.65,
		"time": 1586438401485
	},
	{
		"code": 978,
		"buy": 29.44,
		"sell": 29.8,
		"time": 1586513401316
	},
	{
		"code": 978,
		"buy": 29.4,
		"sell": 29.65,
		"time": 1586855401331
	},
	{
		"code": 978,
		"buy": 29.2,
		"sell": 29.45,
		"time": 1587988801523
	},
	{
		"code": 978,
		"buy": 29.2,
		"sell": 29.45,
		"time": 1588233001567
	},
	{
		"code": 978,
		"buy": 29.1,
		"sell": 29.35,
		"time": 1588663801349
	},
	{
		"code": 978,
		"buy": 29.4,
		"sell": 29.65,
		"time": 1586956801599
	},
	{
		"code": 978,
		"buy": 29.17,
		"sell": 29.35,
		"time": 1587117001096
	},
	{
		"code": 978,
		"buy": 29.2,
		"sell": 29.4,
		"time": 1587123601139
	},
	{
		"code": 978,
		"buy": 29.25,
		"sell": 29.45,
		"time": 1587552601489
	},
	{
		"code": 978,
		"buy": 29.2,
		"sell": 29.45,
		"time": 1587719401119
	},
	{
		"code": 978,
		"buy": 29.5,
		"sell": 29.75,
		"time": 1586938802025
	},
	{
		"code": 978,
		"buy": 29.3,
		"sell": 29.5,
		"time": 1587969001817
	},
	{
		"code": 978,
		"buy": 29.35,
		"sell": 29.7,
		"time": 1586502603428
	},
	{
		"code": 978,
		"buy": 29.45,
		"sell": 29.75,
		"time": 1586515801299
	},
	{
		"code": 978,
		"buy": 29.45,
		"sell": 29.69,
		"time": 1586940601433
	},
	{
		"code": 978,
		"buy": 29.2,
		"sell": 29.45,
		"time": 1587108001217
	},
	{
		"code": 978,
		"buy": 29.1,
		"sell": 29.35,
		"time": 1588150802215
	},
	{
		"code": 978,
		"buy": 29.05,
		"sell": 29.3,
		"time": 1588255202281
	},
	{
		"code": 978,
		"buy": 29.3,
		"sell": 29.53,
		"time": 1587039601168
	},
	{
		"code": 978,
		"buy": 29.25,
		"sell": 29.5,
		"time": 1587131401444
	},
	{
		"code": 978,
		"buy": 28.9,
		"sell": 29.15,
		"time": 1588767001271
	},
	{
		"code": 978,
		"buy": 29.15,
		"sell": 29.55,
		"time": 1586338201694
	},
	{
		"code": 978,
		"buy": 29.3,
		"sell": 29.65,
		"time": 1586351401198
	},
	{
		"code": 978,
		"buy": 29.02,
		"sell": 29.25,
		"time": 1588669801348
	},
	{
		"code": 978,
		"buy": 29.45,
		"sell": 29.75,
		"time": 1586856001246
	},
	{
		"code": 978,
		"buy": 29.3,
		"sell": 29.49,
		"time": 1587549003135
	},
	{
		"code": 978,
		"buy": 29.25,
		"sell": 29.45,
		"time": 1587727801266
	},
	{
		"code": 978,
		"buy": 28.85,
		"sell": 29.1,
		"time": 1588838401722
	},
	{
		"code": 978,
		"buy": 28.87,
		"sell": 29.02,
		"time": 1589283001600
	},
	{
		"code": 978,
		"buy": 28.84,
		"sell": 29,
		"time": 1589362802100
	},
	{
		"code": 978,
		"buy": 29,
		"sell": 29.24,
		"time": 1590391203360
	},
	{
		"code": 978,
		"buy": 29.28,
		"sell": 29.48,
		"time": 1590561003014
	},
	{
		"code": 978,
		"buy": 29.38,
		"sell": 29.53,
		"time": 1590652804354
	},
	{
		"code": 978,
		"buy": 29.87,
		"sell": 30.09,
		"time": 1592318403127
	},
	{
		"code": 978,
		"buy": 29.88,
		"sell": 30.05,
		"time": 1592379004852
	},
	{
		"code": 978,
		"buy": 29.72,
		"sell": 29.92,
		"time": 1593162003461
	},
	{
		"code": 978,
		"buy": 29.69,
		"sell": 29.9,
		"time": 1593504005009
	},
	{
		"code": 978,
		"buy": 29.87,
		"sell": 30.08,
		"time": 1593612602611
	},
	{
		"code": 978,
		"buy": 30.25,
		"sell": 30.47,
		"time": 1594381202315
	},
	{
		"code": 978,
		"buy": 30.75,
		"sell": 30.95,
		"time": 1594819804442
	},
	{
		"code": 978,
		"buy": 29,
		"sell": 29.2,
		"time": 1590135603497
	},
	{
		"code": 978,
		"buy": 29.58,
		"sell": 29.8,
		"time": 1590748802897
	},
	{
		"code": 978,
		"buy": 29.53,
		"sell": 29.72,
		"time": 1591081803181
	},
	{
		"code": 978,
		"buy": 29.85,
		"sell": 30.15,
		"time": 1591338002485
	},
	{
		"code": 978,
		"buy": 29.83,
		"sell": 30.03,
		"time": 1591942803002
	},
	{
		"code": 978,
		"buy": 30.02,
		"sell": 30.24,
		"time": 1591972803951
	},
	{
		"code": 978,
		"buy": 30.63,
		"sell": 30.83,
		"time": 1594800004435
	},
	{
		"code": 978,
		"buy": 30.7,
		"sell": 30.95,
		"time": 1594881002464
	},
	{
		"code": 978,
		"buy": 30.9,
		"sell": 31.1,
		"time": 1594971602496
	},
	{
		"code": 978,
		"buy": 28.67,
		"sell": 28.82,
		"time": 1589787001902
	},
	{
		"code": 978,
		"buy": 28.57,
		"sell": 28.74,
		"time": 1589802001457
	},
	{
		"code": 978,
		"buy": 29.44,
		"sell": 29.66,
		"time": 1590574802386
	},
	{
		"code": 978,
		"buy": 29.64,
		"sell": 29.84,
		"time": 1590993003047
	},
	{
		"code": 978,
		"buy": 29.7,
		"sell": 29.9,
		"time": 1591278005056
	},
	{
		"code": 978,
		"buy": 29.85,
		"sell": 30.05,
		"time": 1592208002974
	},
	{
		"code": 978,
		"buy": 29.9,
		"sell": 30.04,
		"time": 1592388003090
	},
	{
		"code": 978,
		"buy": 29.83,
		"sell": 30.03,
		"time": 1592571003293
	},
	{
		"code": 978,
		"buy": 29.78,
		"sell": 29.98,
		"time": 1593589202720
	},
	{
		"code": 978,
		"buy": 30.27,
		"sell": 30.55,
		"time": 1593757203759
	},
	{
		"code": 978,
		"buy": 30.2,
		"sell": 30.39,
		"time": 1593769206061
	},
	{
		"code": 978,
		"buy": 30.3,
		"sell": 30.5,
		"time": 1594026003492
	},
	{
		"code": 978,
		"buy": 28.75,
		"sell": 28.95,
		"time": 1589878201649
	},
	{
		"code": 978,
		"buy": 28.9,
		"sell": 29.15,
		"time": 1589971802155
	},
	{
		"code": 978,
		"buy": 29.15,
		"sell": 29.35,
		"time": 1590054601848
	},
	{
		"code": 978,
		"buy": 29.35,
		"sell": 29.53,
		"time": 1590564603237
	},
	{
		"code": 978,
		"buy": 29.95,
		"sell": 30.13,
		"time": 1591775403819
	},
	{
		"code": 978,
		"buy": 29.75,
		"sell": 29.95,
		"time": 1592205605269
	},
	{
		"code": 978,
		"buy": 29.86,
		"sell": 30.02,
		"time": 1592916602187
	},
	{
		"code": 978,
		"buy": 30.35,
		"sell": 30.55,
		"time": 1593760803705
	},
	{
		"code": 978,
		"buy": 28.81,
		"sell": 28.97,
		"time": 1589439001757
	},
	{
		"code": 978,
		"buy": 28.87,
		"sell": 29.07,
		"time": 1589961601751
	},
	{
		"code": 978,
		"buy": 29.1,
		"sell": 29.3,
		"time": 1590047402130
	},
	{
		"code": 978,
		"buy": 29.35,
		"sell": 29.5,
		"time": 1590572402342
	},
	{
		"code": 978,
		"buy": 29.72,
		"sell": 29.9,
		"time": 1592203202500
	},
	{
		"code": 978,
		"buy": 29.8,
		"sell": 29.98,
		"time": 1592489406670
	},
	{
		"code": 978,
		"buy": 30.2,
		"sell": 30.4,
		"time": 1594109402862
	},
	{
		"code": 978,
		"buy": 30.7,
		"sell": 30.93,
		"time": 1594804202979
	},
	{
		"code": 978,
		"buy": 30.92,
		"sell": 31.12,
		"time": 1594966802728
	},
	{
		"code": 978,
		"buy": 28.67,
		"sell": 28.82,
		"time": 1589533201911
	},
	{
		"code": 978,
		"buy": 28.7,
		"sell": 28.95,
		"time": 1589872201855
	},
	{
		"code": 978,
		"buy": 28.88,
		"sell": 29.08,
		"time": 1589968201271
	},
	{
		"code": 978,
		"buy": 29.65,
		"sell": 29.8,
		"time": 1591262404428
	},
	{
		"code": 978,
		"buy": 29.82,
		"sell": 30,
		"time": 1591353002559
	},
	{
		"code": 978,
		"buy": 29.97,
		"sell": 30.13,
		"time": 1592296203456
	},
	{
		"code": 978,
		"buy": 29.77,
		"sell": 29.93,
		"time": 1592559602824
	},
	{
		"code": 978,
		"buy": 30.31,
		"sell": 30.6,
		"time": 1594621202238
	},
	{
		"code": 978,
		"buy": 30.54,
		"sell": 30.8,
		"time": 1594710602928
	},
	{
		"code": 978,
		"buy": 30.55,
		"sell": 30.75,
		"time": 1594729204210
	},
	{
		"code": 978,
		"buy": 28.7,
		"sell": 28.85,
		"time": 1589455201528
	},
	{
		"code": 978,
		"buy": 29.18,
		"sell": 29.36,
		"time": 1590483003354
	},
	{
		"code": 978,
		"buy": 29.4,
		"sell": 29.59,
		"time": 1590589803579
	},
	{
		"code": 978,
		"buy": 29.63,
		"sell": 29.83,
		"time": 1590994802700
	},
	{
		"code": 978,
		"buy": 29.8,
		"sell": 30,
		"time": 1592223604448
	},
	{
		"code": 978,
		"buy": 29.82,
		"sell": 29.99,
		"time": 1593065403885
	},
	{
		"code": 978,
		"buy": 30.16,
		"sell": 30.36,
		"time": 1594192803533
	},
	{
		"code": 978,
		"buy": 30.23,
		"sell": 30.43,
		"time": 1594378201817
	},
	{
		"code": 978,
		"buy": 28.73,
		"sell": 28.89,
		"time": 1589441401582
	},
	{
		"code": 978,
		"buy": 29,
		"sell": 29.3,
		"time": 1590042002115
	},
	{
		"code": 978,
		"buy": 29.55,
		"sell": 29.78,
		"time": 1590733803520
	},
	{
		"code": 978,
		"buy": 29.83,
		"sell": 30.03,
		"time": 1591348202611
	},
	{
		"code": 978,
		"buy": 29.95,
		"sell": 30.12,
		"time": 1592382603456
	},
	{
		"code": 978,
		"buy": 30.2,
		"sell": 30.4,
		"time": 1594206603686
	},
	{
		"code": 978,
		"buy": 30.35,
		"sell": 30.6,
		"time": 1594632002219
	},
	{
		"code": 978,
		"buy": 30.5,
		"sell": 30.7,
		"time": 1594715403867
	},
	{
		"code": 978,
		"buy": 29.02,
		"sell": 29.22,
		"time": 1590148805009
	},
	{
		"code": 978,
		"buy": 29.8,
		"sell": 30,
		"time": 1591710603671
	},
	{
		"code": 978,
		"buy": 30,
		"sell": 30.25,
		"time": 1592289003826
	},
	{
		"code": 978,
		"buy": 29.9,
		"sell": 30.1,
		"time": 1592923204886
	},
	{
		"code": 978,
		"buy": 30,
		"sell": 30.24,
		"time": 1593670802323
	},
	{
		"code": 978,
		"buy": 30.3,
		"sell": 30.5,
		"time": 1593763804151
	},
	{
		"code": 978,
		"buy": 30.25,
		"sell": 30.45,
		"time": 1593767404789
	},
	{
		"code": 978,
		"buy": 30.17,
		"sell": 30.35,
		"time": 1594370402506
	},
	{
		"code": 978,
		"buy": 30.5,
		"sell": 30.8,
		"time": 1594708203465
	},
	{
		"code": 978,
		"buy": 28.86,
		"sell": 29.02,
		"time": 1589270401663
	},
	{
		"code": 978,
		"buy": 29.42,
		"sell": 29.57,
		"time": 1590651603855
	},
	{
		"code": 978,
		"buy": 30.05,
		"sell": 30.23,
		"time": 1592292001597
	},
	{
		"code": 978,
		"buy": 29.86,
		"sell": 30.04,
		"time": 1592400602854
	},
	{
		"code": 978,
		"buy": 30.1,
		"sell": 30.34,
		"time": 1594362602492
	},
	{
		"code": 978,
		"buy": 28.9,
		"sell": 29.1,
		"time": 1589970001653
	},
	{
		"code": 978,
		"buy": 29.12,
		"sell": 29.32,
		"time": 1590049801345
	},
	{
		"code": 978,
		"buy": 29.37,
		"sell": 29.57,
		"time": 1590567603288
	},
	{
		"code": 978,
		"buy": 29.75,
		"sell": 29.95,
		"time": 1591363202488
	},
	{
		"code": 978,
		"buy": 29.9,
		"sell": 30.1,
		"time": 1592217602287
	},
	{
		"code": 978,
		"buy": 29.75,
		"sell": 30,
		"time": 1592807403532
	},
	{
		"code": 978,
		"buy": 30.3,
		"sell": 30.55,
		"time": 1594276203128
	},
	{
		"code": 978,
		"buy": 30.77,
		"sell": 30.99,
		"time": 1594894804462
	},
	{
		"code": 978,
		"buy": 28.95,
		"sell": 29.2,
		"time": 1589981401269
	},
	{
		"code": 978,
		"buy": 29.1,
		"sell": 29.3,
		"time": 1590060603976
	},
	{
		"code": 978,
		"buy": 29.22,
		"sell": 29.44,
		"time": 1590489603540
	},
	{
		"code": 978,
		"buy": 29.58,
		"sell": 29.85,
		"time": 1590742804347
	},
	{
		"code": 978,
		"buy": 29.75,
		"sell": 29.95,
		"time": 1591169406446
	},
	{
		"code": 978,
		"buy": 29.67,
		"sell": 29.83,
		"time": 1591254602965
	},
	{
		"code": 978,
		"buy": 29.88,
		"sell": 30.13,
		"time": 1591770603970
	},
	{
		"code": 978,
		"buy": 30.03,
		"sell": 30.19,
		"time": 1592310003483
	},
	{
		"code": 978,
		"buy": 29.75,
		"sell": 29.95,
		"time": 1592552403541
	},
	{
		"code": 978,
		"buy": 29.85,
		"sell": 30.05,
		"time": 1592991603945
	},
	{
		"code": 978,
		"buy": 29.06,
		"sell": 29.24,
		"time": 1590402603705
	},
	{
		"code": 978,
		"buy": 29.6,
		"sell": 29.76,
		"time": 1591005002749
	},
	{
		"code": 978,
		"buy": 30.03,
		"sell": 30.22,
		"time": 1592299202364
	},
	{
		"code": 978,
		"buy": 29.9,
		"sell": 30.09,
		"time": 1592466603818
	},
	{
		"code": 978,
		"buy": 29.71,
		"sell": 29.94,
		"time": 1592814602481
	},
	{
		"code": 978,
		"buy": 29.76,
		"sell": 30.04,
		"time": 1592835002208
	},
	{
		"code": 978,
		"buy": 29.9,
		"sell": 30.08,
		"time": 1592989204355
	},
	{
		"code": 978,
		"buy": 29.86,
		"sell": 30.06,
		"time": 1593002403329
	},
	{
		"code": 978,
		"buy": 30.17,
		"sell": 30.37,
		"time": 1593786003795
	},
	{
		"code": 978,
		"buy": 30.25,
		"sell": 30.4,
		"time": 1594029003630
	},
	{
		"code": 978,
		"buy": 30.15,
		"sell": 30.35,
		"time": 1594113004120
	},
	{
		"code": 978,
		"buy": 31,
		"sell": 31.25,
		"time": 1594980602569
	},
	{
		"code": 978,
		"buy": 29.05,
		"sell": 29.25,
		"time": 1590154204069
	},
	{
		"code": 978,
		"buy": 29.13,
		"sell": 29.33,
		"time": 1590479404036
	},
	{
		"code": 978,
		"buy": 29.72,
		"sell": 29.88,
		"time": 1591186803042
	},
	{
		"code": 978,
		"buy": 29.9,
		"sell": 30.1,
		"time": 1591798803169
	},
	{
		"code": 978,
		"buy": 29.95,
		"sell": 30.15,
		"time": 1591949403074
	},
	{
		"code": 978,
		"buy": 29.77,
		"sell": 29.97,
		"time": 1592896803742
	},
	{
		"code": 978,
		"buy": 30.05,
		"sell": 30.35,
		"time": 1593673803005
	},
	{
		"code": 978,
		"buy": 30.8,
		"sell": 31,
		"time": 1594885802993
	},
	{
		"code": 978,
		"buy": 30.9,
		"sell": 31.1,
		"time": 1594905002782
	},
	{
		"code": 978,
		"buy": 28.65,
		"sell": 28.82,
		"time": 1589529602805
	},
	{
		"code": 978,
		"buy": 28.6,
		"sell": 28.75,
		"time": 1589788801370
	},
	{
		"code": 978,
		"buy": 29,
		"sell": 29.25,
		"time": 1590128403784
	},
	{
		"code": 978,
		"buy": 29.62,
		"sell": 29.8,
		"time": 1591088404705
	},
	{
		"code": 978,
		"buy": 29.87,
		"sell": 30.12,
		"time": 1591341602562
	},
	{
		"code": 978,
		"buy": 30,
		"sell": 30.2,
		"time": 1591952403001
	},
	{
		"code": 978,
		"buy": 29.9,
		"sell": 30.12,
		"time": 1592212204055
	},
	{
		"code": 978,
		"buy": 29.9,
		"sell": 30.07,
		"time": 1592473203660
	},
	{
		"code": 978,
		"buy": 29.88,
		"sell": 30.08,
		"time": 1592985003358
	},
	{
		"code": 978,
		"buy": 29.73,
		"sell": 29.93,
		"time": 1593156604536
	},
	{
		"code": 978,
		"buy": 29.77,
		"sell": 29.97,
		"time": 1593588004223
	},
	{
		"code": 978,
		"buy": 30.25,
		"sell": 30.6,
		"time": 1593675602723
	},
	{
		"code": 978,
		"buy": 30.35,
		"sell": 30.55,
		"time": 1594020602604
	},
	{
		"code": 978,
		"buy": 30.08,
		"sell": 30.3,
		"time": 1594366802999
	},
	{
		"code": 978,
		"buy": 28.7,
		"sell": 28.9,
		"time": 1589551203023
	},
	{
		"code": 978,
		"buy": 28.8,
		"sell": 29,
		"time": 1589887201491
	},
	{
		"code": 978,
		"buy": 29.44,
		"sell": 29.6,
		"time": 1590579002825
	},
	{
		"code": 978,
		"buy": 29.55,
		"sell": 29.7,
		"time": 1591007403400
	},
	{
		"code": 978,
		"buy": 29.95,
		"sell": 30.17,
		"time": 1591867204116
	},
	{
		"code": 978,
		"buy": 30.25,
		"sell": 30.5,
		"time": 1594017002459
	},
	{
		"code": 978,
		"buy": 30.3,
		"sell": 30.5,
		"time": 1594279803175
	},
	{
		"code": 978,
		"buy": 30.35,
		"sell": 30.63,
		"time": 1594626602935
	},
	{
		"code": 978,
		"buy": 30.82,
		"sell": 31,
		"time": 1594903803951
	},
	{
		"code": 978,
		"buy": 31.32,
		"sell": 31.52,
		"time": 1595319004564
	},
	{
		"code": 978,
		"buy": 31.15,
		"sell": 31.4,
		"time": 1595230204889
	},
	{
		"code": 978,
		"buy": 31.42,
		"sell": 31.62,
		"time": 1595329204287
	},
	{
		"code": 978,
		"buy": 31.44,
		"sell": 31.64,
		"time": 1595334604659
	},
	{
		"code": 978,
		"buy": 31.8,
		"sell": 32.2,
		"time": 1595399402680
	},
	{
		"code": 978,
		"buy": 31.3,
		"sell": 31.55,
		"time": 1595236804432
	},
	{
		"code": 978,
		"buy": 31.33,
		"sell": 31.59,
		"time": 1595242204275
	},
	{
		"code": 978,
		"buy": 31.3,
		"sell": 31.57,
		"time": 1595252404273
	},
	{
		"code": 978,
		"buy": 31.37,
		"sell": 31.59,
		"time": 1595322603392
	},
	{
		"code": 978,
		"buy": 31.5,
		"sell": 31.75,
		"time": 1595340005239
	},
	{
		"code": 978,
		"buy": 31.33,
		"sell": 31.59,
		"time": 1595313004923
	},
	{
		"code": 978,
		"buy": 31.23,
		"sell": 31.49,
		"time": 1595233201712
	},
	{
		"code": 978,
		"buy": 31.95,
		"sell": 32.25,
		"time": 1595586602678
	},
	{
		"code": 978,
		"buy": 31.9,
		"sell": 32.15,
		"time": 1595575202405
	},
	{
		"code": 978,
		"buy": 32.18,
		"sell": 32.4,
		"time": 1595844004069
	},
	{
		"code": 978,
		"buy": 32.25,
		"sell": 32.49,
		"time": 1596093605594
	},
	{
		"code": 978,
		"buy": 32.26,
		"sell": 32.48,
		"time": 1596112203571
	},
	{
		"code": 978,
		"buy": 31.92,
		"sell": 32.29,
		"time": 1595485802280
	},
	{
		"code": 978,
		"buy": 32,
		"sell": 32.3,
		"time": 1595595002183
	},
	{
		"code": 978,
		"buy": 32.24,
		"sell": 32.44,
		"time": 1595939404397
	},
	{
		"code": 978,
		"buy": 32,
		"sell": 32.29,
		"time": 1595489403381
	},
	{
		"code": 978,
		"buy": 32.19,
		"sell": 32.64,
		"time": 1595830802579
	},
	{
		"code": 978,
		"buy": 32.15,
		"sell": 32.39,
		"time": 1596026402714
	},
	{
		"code": 978,
		"buy": 31.83,
		"sell": 32.12,
		"time": 1595571602828
	},
	{
		"code": 978,
		"buy": 32.15,
		"sell": 32.4,
		"time": 1596089403923
	},
	{
		"code": 978,
		"buy": 31.9,
		"sell": 32.15,
		"time": 1595514004153
	},
	{
		"code": 978,
		"buy": 32.15,
		"sell": 32.4,
		"time": 1595850604964
	},
	{
		"code": 978,
		"buy": 32.26,
		"sell": 32.5,
		"time": 1596009004115
	},
	{
		"code": 978,
		"buy": 31.75,
		"sell": 32.1,
		"time": 1595403003845
	},
	{
		"code": 978,
		"buy": 31.9,
		"sell": 32.19,
		"time": 1595510402621
	},
	{
		"code": 978,
		"buy": 32.15,
		"sell": 32.38,
		"time": 1595922003189
	},
	{
		"code": 978,
		"buy": 31.87,
		"sell": 32.19,
		"time": 1595422202444
	},
	{
		"code": 978,
		"buy": 32.22,
		"sell": 32.42,
		"time": 1595836804014
	},
	{
		"code": 978,
		"buy": 32.28,
		"sell": 32.5,
		"time": 1596098402223
	},
	{
		"code": 978,
		"buy": 32.5,
		"sell": 32.85,
		"time": 1596176402804
	},
	{
		"code": 978,
		"buy": 32.33,
		"sell": 32.57,
		"time": 1596444601667
	},
	{
		"code": 978,
		"buy": 32.3,
		"sell": 32.58,
		"time": 1596448803899
	},
	{
		"code": 978,
		"buy": 32.52,
		"sell": 32.82,
		"time": 1596637804492
	},
	{
		"code": 978,
		"buy": 32.04,
		"sell": 32.25,
		"time": 1597669804980
	},
	{
		"code": 978,
		"buy": 32.28,
		"sell": 32.52,
		"time": 1597907404149
	},
	{
		"code": 978,
		"buy": 32.35,
		"sell": 32.75,
		"time": 1596608402843
	},
	{
		"code": 978,
		"buy": 32.16,
		"sell": 32.36,
		"time": 1597232402426
	},
	{
		"code": 978,
		"buy": 32.2,
		"sell": 32.4,
		"time": 1597645202791
	},
	{
		"code": 978,
		"buy": 32.1,
		"sell": 32.32,
		"time": 1597653003273
	},
	{
		"code": 978,
		"buy": 32.21,
		"sell": 32.44,
		"time": 1597924202597
	},
	{
		"code": 978,
		"buy": 32.13,
		"sell": 32.36,
		"time": 1598359806440
	},
	{
		"code": 978,
		"buy": 32.35,
		"sell": 32.65,
		"time": 1596460802496
	},
	{
		"code": 978,
		"buy": 32.25,
		"sell": 32.5,
		"time": 1596551406157
	},
	{
		"code": 978,
		"buy": 32.34,
		"sell": 32.6,
		"time": 1597818004033
	},
	{
		"code": 978,
		"buy": 32.1,
		"sell": 32.34,
		"time": 1598008803620
	},
	{
		"code": 978,
		"buy": 32.17,
		"sell": 32.38,
		"time": 1598351404209
	},
	{
		"code": 978,
		"buy": 32.17,
		"sell": 32.42,
		"time": 1598355604118
	},
	{
		"code": 978,
		"buy": 32.4,
		"sell": 32.6,
		"time": 1596802202993
	},
	{
		"code": 978,
		"buy": 32.08,
		"sell": 32.38,
		"time": 1597990805318
	},
	{
		"code": 978,
		"buy": 32.05,
		"sell": 32.31,
		"time": 1598014203968
	},
	{
		"code": 978,
		"buy": 32.55,
		"sell": 32.8,
		"time": 1596187804211
	},
	{
		"code": 978,
		"buy": 32.22,
		"sell": 32.44,
		"time": 1597069204093
	},
	{
		"code": 978,
		"buy": 32.16,
		"sell": 32.39,
		"time": 1597927803669
	},
	{
		"code": 978,
		"buy": 32.14,
		"sell": 32.4,
		"time": 1598422802855
	},
	{
		"code": 978,
		"buy": 32,
		"sell": 32.25,
		"time": 1598427002974
	},
	{
		"code": 978,
		"buy": 32.27,
		"sell": 32.55,
		"time": 1596441003032
	},
	{
		"code": 978,
		"buy": 32.3,
		"sell": 32.55,
		"time": 1596547803383
	},
	{
		"code": 978,
		"buy": 32.5,
		"sell": 32.7,
		"time": 1596787202993
	},
	{
		"code": 978,
		"buy": 32.21,
		"sell": 32.42,
		"time": 1597299604509
	},
	{
		"code": 978,
		"buy": 32.09,
		"sell": 32.34,
		"time": 1598004003301
	},
	{
		"code": 978,
		"buy": 32.54,
		"sell": 32.74,
		"time": 1596703203724
	},
	{
		"code": 978,
		"buy": 32.12,
		"sell": 32.32,
		"time": 1597225804341
	},
	{
		"code": 978,
		"buy": 32.16,
		"sell": 32.38,
		"time": 1597326606630
	},
	{
		"code": 978,
		"buy": 32.55,
		"sell": 32.75,
		"time": 1596786002472
	},
	{
		"code": 978,
		"buy": 32.3,
		"sell": 32.55,
		"time": 1597758603975
	},
	{
		"code": 978,
		"buy": 32.43,
		"sell": 32.66,
		"time": 1597838404535
	},
	{
		"code": 978,
		"buy": 32.06,
		"sell": 32.3,
		"time": 1597932004293
	},
	{
		"code": 978,
		"buy": 32.44,
		"sell": 32.74,
		"time": 1596614402688
	},
	{
		"code": 978,
		"buy": 32.44,
		"sell": 32.66,
		"time": 1596619202594
	},
	{
		"code": 978,
		"buy": 32.14,
		"sell": 32.38,
		"time": 1597386005085
	},
	{
		"code": 978,
		"buy": 32.15,
		"sell": 32.35,
		"time": 1597648802092
	},
	{
		"code": 978,
		"buy": 32.04,
		"sell": 32.25,
		"time": 1597675203352
	},
	{
		"code": 978,
		"buy": 32.05,
		"sell": 32.34,
		"time": 1597735203503
	},
	{
		"code": 978,
		"buy": 32.28,
		"sell": 32.51,
		"time": 1597822803986
	},
	{
		"code": 978,
		"buy": 32.37,
		"sell": 32.6,
		"time": 1597830005462
	},
	{
		"code": 978,
		"buy": 32.05,
		"sell": 32.27,
		"time": 1598000402355
	},
	{
		"code": 978,
		"buy": 32.4,
		"sell": 32.8,
		"time": 1596522003765
	},
	{
		"code": 978,
		"buy": 32.5,
		"sell": 32.78,
		"time": 1596538804283
	},
	{
		"code": 978,
		"buy": 31.6,
		"sell": 32.4,
		"time": 1597674004480
	},
	{
		"code": 978,
		"buy": 32.17,
		"sell": 32.41,
		"time": 1597753204383
	},
	{
		"code": 978,
		"buy": 32.14,
		"sell": 32.37,
		"time": 1598362204136
	},
	{
		"code": 978,
		"buy": 32.09,
		"sell": 32.34,
		"time": 1598432403194
	},
	{
		"code": 978,
		"buy": 32.51,
		"sell": 32.85,
		"time": 1596180603704
	},
	{
		"code": 978,
		"buy": 32.22,
		"sell": 32.42,
		"time": 1597058402293
	},
	{
		"code": 978,
		"buy": 32.1,
		"sell": 32.32,
		"time": 1597218604353
	},
	{
		"code": 978,
		"buy": 32.05,
		"sell": 32.29,
		"time": 1597394404502
	},
	{
		"code": 978,
		"buy": 32.05,
		"sell": 32.25,
		"time": 1597665603800
	},
	{
		"code": 978,
		"buy": 32.1,
		"sell": 32.34,
		"time": 1597738802386
	},
	{
		"code": 978,
		"buy": 32.2,
		"sell": 32.43,
		"time": 1597926004330
	},
	{
		"code": 978,
		"buy": 32.06,
		"sell": 32.26,
		"time": 1598431204483
	},
	{
		"code": 978,
		"buy": 32.17,
		"sell": 32.42,
		"time": 1598436003474
	},
	{
		"code": 978,
		"buy": 32.3,
		"sell": 32.65,
		"time": 1596435002110
	},
	{
		"code": 978,
		"buy": 32.42,
		"sell": 32.7,
		"time": 1596541202309
	},
	{
		"code": 978,
		"buy": 32.25,
		"sell": 32.45,
		"time": 1597138802022
	},
	{
		"code": 978,
		"buy": 32.26,
		"sell": 32.46,
		"time": 1597144805093
	},
	{
		"code": 978,
		"buy": 32.21,
		"sell": 32.47,
		"time": 1597904403161
	},
	{
		"code": 978,
		"buy": 32.35,
		"sell": 32.58,
		"time": 1597909803223
	},
	{
		"code": 978,
		"buy": 32.05,
		"sell": 32.4,
		"time": 1598366405126
	},
	{
		"code": 978,
		"buy": 32.53,
		"sell": 32.8,
		"time": 1596194402888
	},
	{
		"code": 978,
		"buy": 32.15,
		"sell": 32.37,
		"time": 1597213202375
	},
	{
		"code": 978,
		"buy": 32.02,
		"sell": 32.25,
		"time": 1597391403495
	},
	{
		"code": 978,
		"buy": 32.13,
		"sell": 32.39,
		"time": 1598337003683
	},
	{
		"code": 978,
		"buy": 32.09,
		"sell": 32.35,
		"time": 1598433602376
	},
	{
		"code": 978,
		"buy": 32.44,
		"sell": 32.64,
		"time": 1596790202667
	},
	{
		"code": 978,
		"buy": 32.3,
		"sell": 32.55,
		"time": 1596808803971
	},
	{
		"code": 978,
		"buy": 32.08,
		"sell": 32.3,
		"time": 1597654202029
	},
	{
		"code": 978,
		"buy": 32.1,
		"sell": 32.37,
		"time": 1597731003505
	},
	{
		"code": 978,
		"buy": 32.34,
		"sell": 32.57,
		"time": 1597826403977
	},
	{
		"code": 978,
		"buy": 32.55,
		"sell": 32.8,
		"time": 1596535203906
	},
	{
		"code": 978,
		"buy": 32.22,
		"sell": 32.44,
		"time": 1597314003396
	},
	{
		"code": 978,
		"buy": 32.27,
		"sell": 32.54,
		"time": 1597913403022
	},
	{
		"code": 978,
		"buy": 32.19,
		"sell": 32.4,
		"time": 1597996203340
	},
	{
		"code": 978,
		"buy": 32.16,
		"sell": 32.42,
		"time": 1598342406616
	},
	{
		"code": 978,
		"buy": 32.2,
		"sell": 32.4,
		"time": 1598349005215
	},
	{
		"code": 978,
		"buy": 32.45,
		"sell": 32.8,
		"time": 1596527403481
	},
	{
		"code": 978,
		"buy": 32.28,
		"sell": 32.48,
		"time": 1597045804658
	},
	{
		"code": 978,
		"buy": 32.18,
		"sell": 32.4,
		"time": 1597131602581
	},
	{
		"code": 978,
		"buy": 32.22,
		"sell": 32.42,
		"time": 1597304404299
	},
	{
		"code": 978,
		"buy": 32.1,
		"sell": 32.3,
		"time": 1597389005046
	},
	{
		"code": 978,
		"buy": 32.15,
		"sell": 32.39,
		"time": 1597744202860
	},
	{
		"code": 978,
		"buy": 32.27,
		"sell": 32.5,
		"time": 1597916404970
	},
	{
		"code": 978,
		"buy": 32.19,
		"sell": 32.45,
		"time": 1597993803095
	},
	{
		"code": 978,
		"buy": 32.1,
		"sell": 32.38,
		"time": 1598365203895
	},
	{
		"code": 978,
		"buy": 32.1,
		"sell": 32.35,
		"time": 1598446802533
	},
	{
		"code": 978,
		"buy": 32.19,
		"sell": 32.42,
		"time": 1598451002695
	},
	{
		"code": 978,
		"buy": 32.2,
		"sell": 32.44,
		"time": 1598509802870
	},
	{
		"code": 978,
		"buy": 32.2,
		"sell": 32.45,
		"time": 1598514003544
	},
	{
		"code": 978,
		"buy": 32.24,
		"sell": 32.45,
		"time": 1598515808623
	},
	{
		"code": 978,
		"buy": 32.2,
		"sell": 32.44,
		"time": 1598520003040
	},
	{
		"code": 978,
		"buy": 32.15,
		"sell": 32.43,
		"time": 1598526003799
	},
	{
		"code": 978,
		"buy": 32.25,
		"sell": 32.55,
		"time": 1598535602499
	},
	{
		"code": 978,
		"buy": 32.34,
		"sell": 32.58,
		"time": 1598595603714
	},
	{
		"code": 978,
		"buy": 32.41,
		"sell": 32.65,
		"time": 1598601003624
	},
	{
		"code": 978,
		"buy": 32.42,
		"sell": 32.66,
		"time": 1598620204050
	},
	{
		"code": 978,
		"buy": 32.32,
		"sell": 32.6,
		"time": 1598626203619
	},
	{
		"code": 978,
		"buy": 32.4,
		"sell": 32.65,
		"time": 1598855403241
	},
	{
		"code": 978,
		"buy": 32.45,
		"sell": 32.75,
		"time": 1598859605257
	},
	{
		"code": 978,
		"buy": 32.55,
		"sell": 32.8,
		"time": 1598866203382
	},
	{
		"code": 978,
		"buy": 32.48,
		"sell": 32.74,
		"time": 1598868603365
	},
	{
		"code": 978,
		"buy": 32.5,
		"sell": 32.75,
		"time": 1598875802696
	},
	{
		"code": 978,
		"buy": 32.45,
		"sell": 32.78,
		"time": 1598884202932
	},
	{
		"code": 978,
		"buy": 32.6,
		"sell": 32.8,
		"time": 1598941203272
	},
	{
		"code": 978,
		"buy": 32.64,
		"sell": 32.88,
		"time": 1598945404433
	},
	{
		"code": 978,
		"buy": 32.68,
		"sell": 32.9,
		"time": 1598947203014
	},
	{
		"code": 978,
		"buy": 32.77,
		"sell": 33,
		"time": 1598949003676
	},
	{
		"code": 978,
		"buy": 32.68,
		"sell": 32.95,
		"time": 1598950804234
	},
	{
		"code": 978,
		"buy": 32.75,
		"sell": 32.95,
		"time": 1598957405616
	},
	{
		"code": 978,
		"buy": 32.52,
		"sell": 32.84,
		"time": 1598970602858
	},
	{
		"code": 978,
		"buy": 32.5,
		"sell": 32.85,
		"time": 1599028202421
	},
	{
		"code": 978,
		"buy": 32.45,
		"sell": 32.8,
		"time": 1599033604930
	},
	{
		"code": 978,
		"buy": 32.55,
		"sell": 32.8,
		"time": 1599036602355
	},
	{
		"code": 978,
		"buy": 32.5,
		"sell": 32.75,
		"time": 1599048602804
	},
	{
		"code": 978,
		"buy": 32.4,
		"sell": 32.75,
		"time": 1599056402749
	},
	{
		"code": 978,
		"buy": 32.35,
		"sell": 32.75,
		"time": 1599114603815
	},
	{
		"code": 978,
		"buy": 32.45,
		"sell": 32.75,
		"time": 1599116403887
	},
	{
		"code": 978,
		"buy": 32.5,
		"sell": 32.75,
		"time": 1599120003474
	},
	{
		"code": 978,
		"buy": 32.4,
		"sell": 32.65,
		"time": 1599122403498
	},
	{
		"code": 978,
		"buy": 32.45,
		"sell": 32.69,
		"time": 1599127203137
	},
	{
		"code": 978,
		"buy": 32.45,
		"sell": 32.67,
		"time": 1599133202746
	},
	{
		"code": 978,
		"buy": 32.47,
		"sell": 32.75,
		"time": 1599200402902
	},
	{
		"code": 978,
		"buy": 32.54,
		"sell": 32.78,
		"time": 1599204602731
	},
	{
		"code": 978,
		"buy": 32.45,
		"sell": 32.75,
		"time": 1599209402053
	},
	{
		"code": 978,
		"buy": 32.6,
		"sell": 32.77,
		"time": 1599213002742
	},
	{
		"code": 978,
		"buy": 32.35,
		"sell": 32.6,
		"time": 1599228603140
	},
	{
		"code": 978,
		"buy": 32.46,
		"sell": 32.76,
		"time": 1599459603401
	},
	{
		"code": 978,
		"buy": 32.59,
		"sell": 32.75,
		"time": 1599464403374
	},
	{
		"code": 978,
		"buy": 32.55,
		"sell": 32.77,
		"time": 1599475802528
	},
	{
		"code": 978,
		"buy": 32.51,
		"sell": 32.76,
		"time": 1599546602873
	},
	{
		"code": 978,
		"buy": 32.53,
		"sell": 32.74,
		"time": 1599552003961
	},
	{
		"code": 978,
		"buy": 32.6,
		"sell": 32.85,
		"time": 1599554404174
	},
	{
		"code": 978,
		"buy": 32.65,
		"sell": 32.89,
		"time": 1599556206715
	},
	{
		"code": 978,
		"buy": 32.56,
		"sell": 32.79,
		"time": 1599560404551
	},
	{
		"code": 978,
		"buy": 32.55,
		"sell": 32.75,
		"time": 1599633003336
	},
	{
		"code": 978,
		"buy": 32.53,
		"sell": 32.75,
		"time": 1599643202216
	},
	{
		"code": 978,
		"buy": 32.64,
		"sell": 32.9,
		"time": 1599659402334
	},
	{
		"code": 978,
		"buy": 32.65,
		"sell": 32.88,
		"time": 1599718805095
	},
	{
		"code": 978,
		"buy": 32.65,
		"sell": 32.86,
		"time": 1599726003913
	},
	{
		"code": 978,
		"buy": 32.73,
		"sell": 32.9,
		"time": 1599737403974
	},
	{
		"code": 978,
		"buy": 32.82,
		"sell": 33.03,
		"time": 1599743402408
	},
	{
		"code": 978,
		"buy": 32.72,
		"sell": 32.94,
		"time": 1599805202816
	},
	{
		"code": 978,
		"buy": 32.77,
		"sell": 32.95,
		"time": 1599813002711
	},
	{
		"code": 978,
		"buy": 32.82,
		"sell": 33.04,
		"time": 1599813603443
	},
	{
		"code": 978,
		"buy": 32.88,
		"sell": 33.1,
		"time": 1599819602747
	},
	{
		"code": 978,
		"buy": 32.83,
		"sell": 33.05,
		"time": 1599825603172
	},
	{
		"code": 978,
		"buy": 32.94,
		"sell": 33.15,
		"time": 1600069803390
	},
	{
		"code": 978,
		"buy": 32.98,
		"sell": 33.18,
		"time": 1600077604969
	},
	{
		"code": 978,
		"buy": 32.95,
		"sell": 33.16,
		"time": 1600087203628
	},
	{
		"code": 978,
		"buy": 33.03,
		"sell": 33.2,
		"time": 1600150802065
	},
	{
		"code": 978,
		"buy": 33.03,
		"sell": 33.22,
		"time": 1600155602451
	},
	{
		"code": 978,
		"buy": 33.04,
		"sell": 33.23,
		"time": 1600160403104
	},
	{
		"code": 978,
		"buy": 33.06,
		"sell": 33.27,
		"time": 1600162203114
	},
	{
		"code": 978,
		"buy": 33.12,
		"sell": 33.32,
		"time": 1600165802762
	},
	{
		"code": 978,
		"buy": 33.05,
		"sell": 33.26,
		"time": 1600180202469
	},
	{
		"code": 978,
		"buy": 33,
		"sell": 33.21,
		"time": 1600236603382
	},
	{
		"code": 978,
		"buy": 33.08,
		"sell": 33.28,
		"time": 1600240203229
	},
	{
		"code": 978,
		"buy": 33.14,
		"sell": 33.34,
		"time": 1600242602083
	},
	{
		"code": 978,
		"buy": 33.17,
		"sell": 33.35,
		"time": 1600246203762
	},
	{
		"code": 978,
		"buy": 33.14,
		"sell": 33.3,
		"time": 1600252203085
	},
	{
		"code": 978,
		"buy": 33,
		"sell": 33.22,
		"time": 1600260603856
	},
	{
		"code": 978,
		"buy": 32.94,
		"sell": 33.16,
		"time": 1600267802844
	},
	{
		"code": 978,
		"buy": 32.8,
		"sell": 33.05,
		"time": 1600323603213
	},
	{
		"code": 978,
		"buy": 32.85,
		"sell": 33.09,
		"time": 1600327803345
	},
	{
		"code": 978,
		"buy": 32.97,
		"sell": 33.17,
		"time": 1600333204203
	},
	{
		"code": 978,
		"buy": 32.96,
		"sell": 33.18,
		"time": 1600342204197
	},
	{
		"code": 978,
		"buy": 33.12,
		"sell": 33.32,
		"time": 1600410003844
	},
	{
		"code": 978,
		"buy": 33.12,
		"sell": 33.3,
		"time": 1600437006316
	},
	{
		"code": 978,
		"buy": 33.19,
		"sell": 33.35,
		"time": 1600669203547
	},
	{
		"code": 978,
		"buy": 33.1,
		"sell": 33.3,
		"time": 1600675202993
	},
	{
		"code": 978,
		"buy": 33.05,
		"sell": 33.25,
		"time": 1600679406043
	},
	{
		"code": 978,
		"buy": 33.07,
		"sell": 33.29,
		"time": 1600681203963
	},
	{
		"code": 978,
		"buy": 33.1,
		"sell": 33.3,
		"time": 1600690203173
	},
	{
		"code": 978,
		"buy": 33.03,
		"sell": 33.2,
		"time": 1600695603745
	},
	{
		"code": 978,
		"buy": 33,
		"sell": 33.19,
		"time": 1600755602681
	},
	{
		"code": 978,
		"buy": 32.97,
		"sell": 33.17,
		"time": 1600759203998
	},
	{
		"code": 978,
		"buy": 32.84,
		"sell": 33.07,
		"time": 1600761004514
	},
	{
		"code": 978,
		"buy": 32.95,
		"sell": 33.15,
		"time": 1600774203497
	},
	{
		"code": 978,
		"buy": 32.93,
		"sell": 33.15,
		"time": 1600777805838
	},
	{
		"code": 978,
		"buy": 32.82,
		"sell": 33.02,
		"time": 1600842002936
	},
	{
		"code": 978,
		"buy": 32.8,
		"sell": 33,
		"time": 1600847402182
	},
	{
		"code": 978,
		"buy": 32.8,
		"sell": 32.98,
		"time": 1600850403706
	},
	{
		"code": 978,
		"buy": 32.85,
		"sell": 33.04,
		"time": 1600855802688
	},
	{
		"code": 978,
		"buy": 32.78,
		"sell": 33,
		"time": 1600927803131
	},
	{
		"code": 978,
		"buy": 32.82,
		"sell": 33.02,
		"time": 1600936204610
	},
	{
		"code": 978,
		"buy": 32.7,
		"sell": 32.9,
		"time": 1600952403240
	},
	{
		"code": 978,
		"buy": 32.82,
		"sell": 33.03,
		"time": 1601015405106
	},
	{
		"code": 978,
		"buy": 32.72,
		"sell": 32.99,
		"time": 1601028603065
	},
	{
		"code": 978,
		"buy": 32.72,
		"sell": 32.98,
		"time": 1601040003725
	},
	{
		"code": 978,
		"buy": 32.7,
		"sell": 32.93,
		"time": 1601274004684
	},
	{
		"code": 978,
		"buy": 32.74,
		"sell": 32.98,
		"time": 1601278205337
	},
	{
		"code": 978,
		"buy": 32.75,
		"sell": 32.99,
		"time": 1601285404256
	},
	{
		"code": 978,
		"buy": 32.85,
		"sell": 33.08,
		"time": 1601293802666
	},
	{
		"code": 978,
		"buy": 32.82,
		"sell": 33.07,
		"time": 1601298602360
	},
	{
		"code": 978,
		"buy": 32.8,
		"sell": 33.05,
		"time": 1601360404000
	},
	{
		"code": 978,
		"buy": 32.82,
		"sell": 33.05,
		"time": 1601364604791
	},
	{
		"code": 978,
		"buy": 32.9,
		"sell": 33.1,
		"time": 1601373004453
	},
	{
		"code": 978,
		"buy": 32.93,
		"sell": 33.15,
		"time": 1601386203655
	},
	{
		"code": 978,
		"buy": 33.05,
		"sell": 33.25,
		"time": 1601447404991
	},
	{
		"code": 978,
		"buy": 33.01,
		"sell": 33.21,
		"time": 1601452203062
	},
	{
		"code": 978,
		"buy": 33.02,
		"sell": 33.22,
		"time": 1601453403186
	},
	{
		"code": 978,
		"buy": 32.95,
		"sell": 33.15,
		"time": 1601458207491
	},
	{
		"code": 978,
		"buy": 33.07,
		"sell": 33.27,
		"time": 1601533203398
	},
	{
		"code": 978,
		"buy": 33.05,
		"sell": 33.24,
		"time": 1601539804811
	},
	{
		"code": 978,
		"buy": 33.02,
		"sell": 33.21,
		"time": 1601542802893
	},
	{
		"code": 978,
		"buy": 33.09,
		"sell": 33.3,
		"time": 1601546403263
	},
	{
		"code": 978,
		"buy": 33.12,
		"sell": 33.34,
		"time": 1601553003607
	},
	{
		"code": 978,
		"buy": 33.06,
		"sell": 33.28,
		"time": 1601562004560
	},
	{
		"code": 978,
		"buy": 33.06,
		"sell": 33.29,
		"time": 1601619604476
	},
	{
		"code": 978,
		"buy": 33.05,
		"sell": 33.25,
		"time": 1601631003095
	},
	{
		"code": 978,
		"buy": 33.06,
		"sell": 33.28,
		"time": 1601878803429
	},
	{
		"code": 978,
		"buy": 33.1,
		"sell": 33.35,
		"time": 1601880603691
	},
	{
		"code": 978,
		"buy": 33.22,
		"sell": 33.45,
		"time": 1601892603683
	},
	{
		"code": 978,
		"buy": 33.21,
		"sell": 33.4,
		"time": 1601896202672
	},
	{
		"code": 978,
		"buy": 33.28,
		"sell": 33.51,
		"time": 1601965805734
	},
	{
		"code": 978,
		"buy": 33.25,
		"sell": 33.47,
		"time": 1601971804685
	},
	{
		"code": 978,
		"buy": 33.18,
		"sell": 33.39,
		"time": 1601976005057
	},
	{
		"code": 978,
		"buy": 33.25,
		"sell": 33.45,
		"time": 1601983806085
	},
	{
		"code": 978,
		"buy": 33.2,
		"sell": 33.4,
		"time": 1601990406389
	},
	{
		"code": 978,
		"buy": 33.05,
		"sell": 33.33,
		"time": 1602051602821
	},
	{
		"code": 978,
		"buy": 33.1,
		"sell": 33.32,
		"time": 1602058204721
	},
	{
		"code": 978,
		"buy": 33.13,
		"sell": 33.35,
		"time": 1602075004047
	},
	{
		"code": 978,
		"buy": 33.1,
		"sell": 33.34,
		"time": 1602137404041
	},
	{
		"code": 978,
		"buy": 33.07,
		"sell": 33.29,
		"time": 1602141004003
	},
	{
		"code": 978,
		"buy": 33.02,
		"sell": 33.25,
		"time": 1602147003545
	},
	{
		"code": 978,
		"buy": 33,
		"sell": 33.24,
		"time": 1602155403248
	},
	{
		"code": 978,
		"buy": 32.98,
		"sell": 33.23,
		"time": 1602160803486
	},
	{
		"code": 978,
		"buy": 33.01,
		"sell": 33.25,
		"time": 1602224402936
	},
	{
		"code": 978,
		"buy": 33,
		"sell": 33.2,
		"time": 1602230403687
	},
	{
		"code": 978,
		"buy": 33.08,
		"sell": 33.28,
		"time": 1602232205148
	},
	{
		"code": 978,
		"buy": 33.06,
		"sell": 33.26,
		"time": 1602237003519
	},
	{
		"code": 978,
		"buy": 33.09,
		"sell": 33.29,
		"time": 1602246003965
	},
	{
		"code": 978,
		"buy": 33.15,
		"sell": 33.35,
		"time": 1602251405536
	},
	{
		"code": 978,
		"buy": 33.25,
		"sell": 33.5,
		"time": 1602483005305
	},
	{
		"code": 978,
		"buy": 33.24,
		"sell": 33.45,
		"time": 1602488403205
	},
	{
		"code": 978,
		"buy": 33.15,
		"sell": 33.39,
		"time": 1602489003829
	},
	{
		"code": 978,
		"buy": 33.16,
		"sell": 33.37,
		"time": 1602504002914
	},
	{
		"code": 978,
		"buy": 33.2,
		"sell": 33.4,
		"time": 1602575404836
	},
	{
		"code": 978,
		"buy": 33.22,
		"sell": 33.42,
		"time": 1602579003607
	},
	{
		"code": 978,
		"buy": 33.16,
		"sell": 33.39,
		"time": 1602596404885
	},
	{
		"code": 978,
		"buy": 33.14,
		"sell": 33.36,
		"time": 1602742803004
	},
	{
		"code": 978,
		"buy": 33.07,
		"sell": 33.27,
		"time": 1602751804611
	},
	{
		"code": 978,
		"buy": 33.02,
		"sell": 33.25,
		"time": 1602753604092
	},
	{
		"code": 978,
		"buy": 33,
		"sell": 33.22,
		"time": 1602768003086
	},
	{
		"code": 978,
		"buy": 33.03,
		"sell": 33.23,
		"time": 1602835804167
	},
	{
		"code": 978,
		"buy": 33.09,
		"sell": 33.32,
		"time": 1602855605437
	},
	{
		"code": 978,
		"buy": 33.05,
		"sell": 33.25,
		"time": 1602859205148
	},
	{
		"code": 978,
		"buy": 33.03,
		"sell": 33.23,
		"time": 1603087803972
	},
	{
		"code": 978,
		"buy": 33.05,
		"sell": 33.3,
		"time": 1603092605772
	},
	{
		"code": 978,
		"buy": 33.15,
		"sell": 33.38,
		"time": 1603100403839
	},
	{
		"code": 978,
		"buy": 33.2,
		"sell": 33.46,
		"time": 1603106404522
	},
	{
		"code": 978,
		"buy": 33.24,
		"sell": 33.5,
		"time": 1603174203757
	},
	{
		"code": 978,
		"buy": 33.24,
		"sell": 33.48,
		"time": 1603183803176
	},
	{
		"code": 978,
		"buy": 33.3,
		"sell": 33.5,
		"time": 1603189802580
	},
	{
		"code": 978,
		"buy": 33.28,
		"sell": 33.48,
		"time": 1603198803398
	},
	{
		"code": 978,
		"buy": 33.4,
		"sell": 33.6,
		"time": 1603261203188
	},
	{
		"code": 978,
		"buy": 33.37,
		"sell": 33.58,
		"time": 1603267203455
	},
	{
		"code": 978,
		"buy": 33.33,
		"sell": 33.53,
		"time": 1603269602812
	},
	{
		"code": 978,
		"buy": 33.36,
		"sell": 33.57,
		"time": 1603273204958
	},
	{
		"code": 978,
		"buy": 33.34,
		"sell": 33.54,
		"time": 1603282803094
	},
	{
		"code": 978,
		"buy": 33.32,
		"sell": 33.52,
		"time": 1603347604062
	},
	{
		"code": 978,
		"buy": 33.33,
		"sell": 33.53,
		"time": 1603359604953
	},
	{
		"code": 978,
		"buy": 33.28,
		"sell": 33.48,
		"time": 1603368007972
	},
	{
		"code": 978,
		"buy": 33.25,
		"sell": 33.48,
		"time": 1603434003839
	},
	{
		"code": 978,
		"buy": 33.3,
		"sell": 33.5,
		"time": 1603441202749
	},
	{
		"code": 978,
		"buy": 33.35,
		"sell": 33.55,
		"time": 1603443611716
	},
	{
		"code": 978,
		"buy": 33.36,
		"sell": 33.56,
		"time": 1603453202884
	},
	{
		"code": 978,
		"buy": 33.37,
		"sell": 33.6,
		"time": 1603461003560
	},
	{
		"code": 978,
		"buy": 33.4,
		"sell": 33.6,
		"time": 1603696206561
	},
	{
		"code": 978,
		"buy": 33.3,
		"sell": 33.5,
		"time": 1603705203719
	},
	{
		"code": 978,
		"buy": 33.34,
		"sell": 33.54,
		"time": 1603713605371
	},
	{
		"code": 978,
		"buy": 33.37,
		"sell": 33.6,
		"time": 1603782603196
	},
	{
		"code": 978,
		"buy": 33.36,
		"sell": 33.56,
		"time": 1603788605008
	},
	{
		"code": 978,
		"buy": 33.42,
		"sell": 33.65,
		"time": 1603803002899
	},
	{
		"code": 978,
		"buy": 33.3,
		"sell": 33.5,
		"time": 1603869003649
	},
	{
		"code": 978,
		"buy": 33.25,
		"sell": 33.45,
		"time": 1603875004299
	},
	{
		"code": 978,
		"buy": 33.25,
		"sell": 33.48,
		"time": 1603956004220
	},
	{
		"code": 978,
		"buy": 33.22,
		"sell": 33.42,
		"time": 1603959603655
	},
	{
		"code": 978,
		"buy": 33.2,
		"sell": 33.4,
		"time": 1603968003278
	},
	{
		"code": 978,
		"buy": 33.16,
		"sell": 33.4,
		"time": 1603974603784
	},
	{
		"code": 978,
		"buy": 33.1,
		"sell": 33.34,
		"time": 1603986003320
	},
	{
		"code": 978,
		"buy": 33.1,
		"sell": 33.3,
		"time": 1604041803858
	},
	{
		"code": 978,
		"buy": 33.15,
		"sell": 33.39,
		"time": 1604068803058
	},
	{
		"code": 978,
		"buy": 33.02,
		"sell": 33.28,
		"time": 1604301603456
	},
	{
		"code": 978,
		"buy": 33.06,
		"sell": 33.3,
		"time": 1604305803417
	},
	{
		"code": 978,
		"buy": 33.17,
		"sell": 33.4,
		"time": 1604311204613
	},
	{
		"code": 978,
		"buy": 33.2,
		"sell": 33.44,
		"time": 1604313004397
	},
	{
		"code": 978,
		"buy": 33.25,
		"sell": 33.52,
		"time": 1604388003124
	},
	{
		"code": 978,
		"buy": 33.28,
		"sell": 33.48,
		"time": 1604398802919
	},
	{
		"code": 978,
		"buy": 33.3,
		"sell": 33.48,
		"time": 1604408403730
	},
	{
		"code": 978,
		"buy": 33.12,
		"sell": 33.38,
		"time": 1604474403491
	},
	{
		"code": 978,
		"buy": 33.14,
		"sell": 33.4,
		"time": 1604479803575
	},
	{
		"code": 978,
		"buy": 33.2,
		"sell": 33.4,
		"time": 1604487604761
	},
	{
		"code": 978,
		"buy": 33.23,
		"sell": 33.45,
		"time": 1604494203751
	},
	{
		"code": 978,
		"buy": 33.15,
		"sell": 33.35,
		"time": 1604499604873
	},
	{
		"code": 978,
		"buy": 33.22,
		"sell": 33.46,
		"time": 1604561402947
	},
	{
		"code": 978,
		"buy": 33.32,
		"sell": 33.52,
		"time": 1604566804423
	},
	{
		"code": 978,
		"buy": 33.26,
		"sell": 33.46,
		"time": 1604569802777
	},
	{
		"code": 978,
		"buy": 33.33,
		"sell": 33.55,
		"time": 1604572802731
	},
	{
		"code": 978,
		"buy": 33.23,
		"sell": 33.46,
		"time": 1604575204323
	},
	{
		"code": 978,
		"buy": 33.3,
		"sell": 33.5,
		"time": 1604646605657
	},
	{
		"code": 978,
		"buy": 33.2,
		"sell": 33.45,
		"time": 1604654403874
	},
	{
		"code": 978,
		"buy": 33.14,
		"sell": 33.34,
		"time": 1604655603517
	},
	{
		"code": 978,
		"buy": 33.25,
		"sell": 33.44,
		"time": 1604661003647
	},
	{
		"code": 978,
		"buy": 33.31,
		"sell": 33.5,
		"time": 1604669404036
	},
	{
		"code": 978,
		"buy": 33.27,
		"sell": 33.47,
		"time": 1604675403790
	},
	{
		"code": 978,
		"buy": 33.4,
		"sell": 33.65,
		"time": 1604905803931
	},
	{
		"code": 978,
		"buy": 33.35,
		"sell": 33.65,
		"time": 1604909403784
	},
	{
		"code": 978,
		"buy": 33.32,
		"sell": 33.54,
		"time": 1604912404376
	},
	{
		"code": 978,
		"buy": 33.23,
		"sell": 33.43,
		"time": 1604916604779
	},
	{
		"code": 978,
		"buy": 33.28,
		"sell": 33.45,
		"time": 1604927403144
	},
	{
		"code": 978,
		"buy": 33.2,
		"sell": 33.45,
		"time": 1604992803387
	},
	{
		"code": 978,
		"buy": 33.15,
		"sell": 33.35,
		"time": 1604998202510
	},
	{
		"code": 978,
		"buy": 33.08,
		"sell": 33.28,
		"time": 1605004202671
	},
	{
		"code": 978,
		"buy": 33.1,
		"sell": 33.3,
		"time": 1605010803093
	},
	{
		"code": 978,
		"buy": 33.2,
		"sell": 33.4,
		"time": 1605020403416
	},
	{
		"code": 978,
		"buy": 33.23,
		"sell": 33.48,
		"time": 1605078603691
	},
	{
		"code": 978,
		"buy": 33.13,
		"sell": 33.33,
		"time": 1605085204450
	},
	{
		"code": 978,
		"buy": 33.1,
		"sell": 33.3,
		"time": 1605095403031
	},
	{
		"code": 978,
		"buy": 33.06,
		"sell": 33.26,
		"time": 1605100804583
	},
	{
		"code": 978,
		"buy": 33,
		"sell": 33.27,
		"time": 1605106803353
	},
	{
		"code": 978,
		"buy": 33.05,
		"sell": 33.3,
		"time": 1605165604308
	},
	{
		"code": 978,
		"buy": 33.17,
		"sell": 33.32,
		"time": 1605171603923
	},
	{
		"code": 978,
		"buy": 33.21,
		"sell": 33.37,
		"time": 1605177003486
	},
	{
		"code": 978,
		"buy": 33.19,
		"sell": 33.33,
		"time": 1605186005674
	},
	{
		"code": 978,
		"buy": 33.16,
		"sell": 33.36,
		"time": 1605255603643
	},
	{
		"code": 978,
		"buy": 33.1,
		"sell": 33.28,
		"time": 1605258603642
	},
	{
		"code": 978,
		"buy": 33.25,
		"sell": 33.55,
		"time": 1605511202253
	},
	{
		"code": 978,
		"buy": 33.22,
		"sell": 33.39,
		"time": 1605519002929
	},
	{
		"code": 978,
		"buy": 33.2,
		"sell": 33.35,
		"time": 1605522002809
	},
	{
		"code": 978,
		"buy": 33.15,
		"sell": 33.3,
		"time": 1605534602885
	},
	{
		"code": 978,
		"buy": 33.21,
		"sell": 33.39,
		"time": 1605597005120
	},
	{
		"code": 978,
		"buy": 33.2,
		"sell": 33.35,
		"time": 1605606602374
	},
	{
		"code": 978,
		"buy": 33.21,
		"sell": 33.39,
		"time": 1605615603655
	},
	{
		"code": 978,
		"buy": 33.27,
		"sell": 33.47,
		"time": 1605622204205
	},
	{
		"code": 978,
		"buy": 33.3,
		"sell": 33.48,
		"time": 1605688803456
	},
	{
		"code": 978,
		"buy": 33.28,
		"sell": 33.44,
		"time": 1605707403260
	},
	{
		"code": 978,
		"buy": 33.3,
		"sell": 33.48,
		"time": 1605770404003
	},
	{
		"code": 978,
		"buy": 33.28,
		"sell": 33.43,
		"time": 1605775803195
	},
	{
		"code": 978,
		"buy": 33.26,
		"sell": 33.44,
		"time": 1605779402798
	},
	{
		"code": 978,
		"buy": 33.3,
		"sell": 33.45,
		"time": 1605784804329
	},
	{
		"code": 978,
		"buy": 33.35,
		"sell": 33.53,
		"time": 1605787803852
	},
	{
		"code": 978,
		"buy": 33.45,
		"sell": 33.69,
		"time": 1605857403327
	},
	{
		"code": 978,
		"buy": 33.5,
		"sell": 33.68,
		"time": 1605867003325
	},
	{
		"code": 978,
		"buy": 33.48,
		"sell": 33.65,
		"time": 1605871203052
	},
	{
		"code": 978,
		"buy": 33.47,
		"sell": 33.67,
		"time": 1605879603718
	},
	{
		"code": 978,
		"buy": 33.45,
		"sell": 33.65,
		"time": 1605885003383
	},
	{
		"code": 978,
		"buy": 33.48,
		"sell": 33.68,
		"time": 1606116003884
	},
	{
		"code": 978,
		"buy": 33.52,
		"sell": 33.69,
		"time": 1606123203276
	},
	{
		"code": 978,
		"buy": 33.56,
		"sell": 33.76,
		"time": 1606136407915
	},
	{
		"code": 978,
		"buy": 33.35,
		"sell": 33.6,
		"time": 1606145403838
	},
	{
		"code": 978,
		"buy": 33.42,
		"sell": 33.62,
		"time": 1606202403412
	},
	{
		"code": 978,
		"buy": 33.47,
		"sell": 33.67,
		"time": 1606206603709
	},
	{
		"code": 978,
		"buy": 33.5,
		"sell": 33.7,
		"time": 1606216802537
	},
	{
		"code": 978,
		"buy": 33.48,
		"sell": 33.65,
		"time": 1606222209887
	},
	{
		"code": 978,
		"buy": 33.5,
		"sell": 33.7,
		"time": 1606288803500
	},
	{
		"code": 978,
		"buy": 33.55,
		"sell": 33.75,
		"time": 1606294805708
	},
	{
		"code": 978,
		"buy": 33.57,
		"sell": 33.77,
		"time": 1606307403388
	},
	{
		"code": 978,
		"buy": 33.6,
		"sell": 33.8,
		"time": 1606315204482
	},
	{
		"code": 978,
		"buy": 33.65,
		"sell": 33.85,
		"time": 1606375203605
	},
	{
		"code": 978,
		"buy": 33.7,
		"sell": 33.9,
		"time": 1606381204506
	},
	{
		"code": 978,
		"buy": 33.65,
		"sell": 33.85,
		"time": 1606386002709
	},
	{
		"code": 978,
		"buy": 33.7,
		"sell": 33.85,
		"time": 1606402803703
	},
	{
		"code": 978,
		"buy": 33.7,
		"sell": 33.92,
		"time": 1606461603489
	},
	{
		"code": 978,
		"buy": 33.75,
		"sell": 33.93,
		"time": 1606468204384
	},
	{
		"code": 978,
		"buy": 33.75,
		"sell": 33.92,
		"time": 1606474803325
	},
	{
		"code": 978,
		"buy": 33.75,
		"sell": 33.93,
		"time": 1606478403309
	},
	{
		"code": 978,
		"buy": 33.8,
		"sell": 34.05,
		"time": 1606489803971
	},
	{
		"code": 978,
		"buy": 33.9,
		"sell": 34.12,
		"time": 1606725604258
	},
	{
		"code": 978,
		"buy": 33.9,
		"sell": 34.09,
		"time": 1606727404322
	},
	{
		"code": 978,
		"buy": 33.95,
		"sell": 34.15,
		"time": 1606750804117
	},
	{
		"code": 978,
		"buy": 33.86,
		"sell": 34.06,
		"time": 1606806604546
	},
	{
		"code": 978,
		"buy": 33.98,
		"sell": 34.13,
		"time": 1606812003170
	},
	{
		"code": 978,
		"buy": 34,
		"sell": 34.15,
		"time": 1606818603704
	},
	{
		"code": 978,
		"buy": 33.95,
		"sell": 34.1,
		"time": 1606830603650
	},
	{
		"code": 978,
		"buy": 34.18,
		"sell": 34.38,
		"time": 1606893601942
	},
	{
		"code": 978,
		"buy": 34.2,
		"sell": 34.38,
		"time": 1606896604637
	},
	{
		"code": 978,
		"buy": 34.1,
		"sell": 34.25,
		"time": 1606899003951
	},
	{
		"code": 978,
		"buy": 34.05,
		"sell": 34.2,
		"time": 1606914004981
	},
	{
		"code": 978,
		"buy": 34.15,
		"sell": 34.3,
		"time": 1606980004439
	},
	{
		"code": 978,
		"buy": 34.14,
		"sell": 34.29,
		"time": 1606985403327
	},
	{
		"code": 978,
		"buy": 34.15,
		"sell": 34.34,
		"time": 1606992005344
	},
	{
		"code": 978,
		"buy": 34.23,
		"sell": 34.38,
		"time": 1606998604420
	},
	{
		"code": 978,
		"buy": 34.19,
		"sell": 34.39,
		"time": 1607002206280
	},
	{
		"code": 978,
		"buy": 34.2,
		"sell": 34.38,
		"time": 1607066403979
	},
	{
		"code": 978,
		"buy": 34.25,
		"sell": 34.4,
		"time": 1607071805371
	},
	{
		"code": 978,
		"buy": 34.28,
		"sell": 34.43,
		"time": 1607079605372
	},
	{
		"code": 978,
		"buy": 34.2,
		"sell": 34.39,
		"time": 1607088004155
	},
	{
		"code": 978,
		"buy": 34.22,
		"sell": 34.39,
		"time": 1607094004542
	},
	{
		"code": 978,
		"buy": 34.08,
		"sell": 34.27,
		"time": 1607325004147
	},
	{
		"code": 978,
		"buy": 34.14,
		"sell": 34.32,
		"time": 1607329204358
	},
	{
		"code": 978,
		"buy": 34.1,
		"sell": 34.29,
		"time": 1607330405791
	},
	{
		"code": 978,
		"buy": 34.09,
		"sell": 34.29,
		"time": 1607332203539
	},
	{
		"code": 978,
		"buy": 34.03,
		"sell": 34.2,
		"time": 1607338804362
	},
	{
		"code": 978,
		"buy": 34.05,
		"sell": 34.2,
		"time": 1607350803560
	},
	{
		"code": 978,
		"buy": 33.93,
		"sell": 34.21,
		"time": 1607412002452
	},
	{
		"code": 978,
		"buy": 33.9,
		"sell": 34.05,
		"time": 1607416802846
	},
	{
		"code": 978,
		"buy": 33.95,
		"sell": 34.1,
		"time": 1607419802412
	},
	{
		"code": 978,
		"buy": 34.02,
		"sell": 34.22,
		"time": 1607497804097
	},
	{
		"code": 978,
		"buy": 33.94,
		"sell": 34.09,
		"time": 1607500804653
	},
	{
		"code": 978,
		"buy": 33.9,
		"sell": 34.05,
		"time": 1607510404509
	},
	{
		"code": 978,
		"buy": 33.85,
		"sell": 34,
		"time": 1607516404143
	},
	{
		"code": 978,
		"buy": 33.92,
		"sell": 34.07,
		"time": 1607526004169
	},
	{
		"code": 978,
		"buy": 33.83,
		"sell": 34,
		"time": 1607528403485
	},
	{
		"code": 978,
		"buy": 33.84,
		"sell": 34.04,
		"time": 1607584802295
	},
	{
		"code": 978,
		"buy": 33.92,
		"sell": 34.09,
		"time": 1607594403488
	},
	{
		"code": 978,
		"buy": 33.84,
		"sell": 34,
		"time": 1607603403108
	},
	{
		"code": 978,
		"buy": 33.9,
		"sell": 34.05,
		"time": 1607608204044
	},
	{
		"code": 978,
		"buy": 33.95,
		"sell": 34.15,
		"time": 1607671202071
	},
	{
		"code": 978,
		"buy": 33.9,
		"sell": 34.1,
		"time": 1607674203806
	},
	{
		"code": 978,
		"buy": 33.8,
		"sell": 34,
		"time": 1607676004566
	},
	{
		"code": 978,
		"buy": 33.85,
		"sell": 34,
		"time": 1607692802356
	},
	{
		"code": 978,
		"buy": 33.8,
		"sell": 34,
		"time": 1607931004093
	},
	{
		"code": 978,
		"buy": 33.77,
		"sell": 33.97,
		"time": 1607935203778
	},
	{
		"code": 978,
		"buy": 33.75,
		"sell": 33.95,
		"time": 1607937603613
	},
	{
		"code": 978,
		"buy": 33.75,
		"sell": 33.93,
		"time": 1607946603395
	},
	{
		"code": 978,
		"buy": 33.72,
		"sell": 33.9,
		"time": 1607952003526
	},
	{
		"code": 978,
		"buy": 33.68,
		"sell": 33.85,
		"time": 1607958003347
	},
	{
		"code": 978,
		"buy": 33.6,
		"sell": 33.85,
		"time": 1607959804226
	},
	{
		"code": 978,
		"buy": 33.73,
		"sell": 33.9,
		"time": 1608016802672
	},
	{
		"code": 978,
		"buy": 33.6,
		"sell": 33.8,
		"time": 1608020404799
	},
	{
		"code": 978,
		"buy": 33.57,
		"sell": 33.75,
		"time": 1608023403996
	},
	{
		"code": 978,
		"buy": 33.57,
		"sell": 33.77,
		"time": 1608026403752
	},
	{
		"code": 978,
		"buy": 33.45,
		"sell": 33.65,
		"time": 1608038404400
	},
	{
		"code": 978,
		"buy": 33.55,
		"sell": 33.75,
		"time": 1608042004273
	},
	{
		"code": 978,
		"buy": 33.58,
		"sell": 33.75,
		"time": 1608103804231
	},
	{
		"code": 978,
		"buy": 33.52,
		"sell": 33.74,
		"time": 1608104404328
	},
	{
		"code": 978,
		"buy": 33.64,
		"sell": 33.86,
		"time": 1608111604472
	},
	{
		"code": 978,
		"buy": 33.75,
		"sell": 33.95,
		"time": 1608116404215
	},
	{
		"code": 978,
		"buy": 33.8,
		"sell": 33.99,
		"time": 1608132604998
	},
	{
		"code": 978,
		"buy": 33.87,
		"sell": 34.09,
		"time": 1608189004708
	},
	{
		"code": 978,
		"buy": 33.83,
		"sell": 34.03,
		"time": 1608196204433
	},
	{
		"code": 978,
		"buy": 33.89,
		"sell": 34.1,
		"time": 1608202804436
	},
	{
		"code": 978,
		"buy": 33.9,
		"sell": 34.1,
		"time": 1608276002433
	},
	{
		"code": 978,
		"buy": 33.8,
		"sell": 34,
		"time": 1608279601915
	},
	{
		"code": 978,
		"buy": 33.9,
		"sell": 34.1,
		"time": 1608282604824
	},
	{
		"code": 978,
		"buy": 33.93,
		"sell": 34.13,
		"time": 1608290404564
	},
	{
		"code": 978,
		"buy": 34,
		"sell": 34.25,
		"time": 1608298804845
	},
	{
		"code": 978,
		"buy": 33.85,
		"sell": 34.18,
		"time": 1608534604116
	},
	{
		"code": 978,
		"buy": 33.75,
		"sell": 34,
		"time": 1608539404767
	},
	{
		"code": 978,
		"buy": 33.85,
		"sell": 34.1,
		"time": 1608540604666
	},
	{
		"code": 978,
		"buy": 33.85,
		"sell": 34.14,
		"time": 1608544804130
	},
	{
		"code": 978,
		"buy": 33.9,
		"sell": 34.19,
		"time": 1608546003942
	},
	{
		"code": 978,
		"buy": 33.9,
		"sell": 34.18,
		"time": 1608549004699
	},
	{
		"code": 978,
		"buy": 33.95,
		"sell": 34.2,
		"time": 1608552605157
	},
	{
		"code": 978,
		"buy": 34,
		"sell": 34.3,
		"time": 1608556803999
	},
	{
		"code": 978,
		"buy": 34.13,
		"sell": 34.4,
		"time": 1608562804367
	},
	{
		"code": 978,
		"buy": 34.13,
		"sell": 34.43,
		"time": 1608565204096
	},
	{
		"code": 978,
		"buy": 34.15,
		"sell": 34.45,
		"time": 1608621604255
	},
	{
		"code": 978,
		"buy": 34.14,
		"sell": 34.4,
		"time": 1608625206283
	},
	{
		"code": 978,
		"buy": 34.2,
		"sell": 34.44,
		"time": 1608627605533
	},
	{
		"code": 978,
		"buy": 34.3,
		"sell": 34.6,
		"time": 1608635404837
	},
	{
		"code": 978,
		"buy": 34.35,
		"sell": 34.7,
		"time": 1608648603507
	},
	{
		"code": 978,
		"buy": 34.31,
		"sell": 34.6,
		"time": 1608707402695
	},
	{
		"code": 978,
		"buy": 34.3,
		"sell": 34.6,
		"time": 1608712804607
	},
	{
		"code": 978,
		"buy": 34.37,
		"sell": 34.7,
		"time": 1608717004326
	},
	{
		"code": 978,
		"buy": 34.35,
		"sell": 34.65,
		"time": 1608722404527
	},
	{
		"code": 978,
		"buy": 34.25,
		"sell": 34.55,
		"time": 1608730803363
	},
	{
		"code": 978,
		"buy": 34.34,
		"sell": 34.64,
		"time": 1608794403569
	},
	{
		"code": 978,
		"buy": 34.3,
		"sell": 34.6,
		"time": 1608798002676
	},
	{
		"code": 978,
		"buy": 34.2,
		"sell": 34.49,
		"time": 1608799802638
	},
	{
		"code": 978,
		"buy": 34.21,
		"sell": 34.57,
		"time": 1608818404943
	},
	{
		"code": 978,
		"buy": 34.2,
		"sell": 34.6,
		"time": 1609140004118
	},
	{
		"code": 978,
		"buy": 34.18,
		"sell": 34.54,
		"time": 1609145403027
	},
	{
		"code": 978,
		"buy": 34.2,
		"sell": 34.55,
		"time": 1609149603746
	},
	{
		"code": 978,
		"buy": 34.15,
		"sell": 34.48,
		"time": 1609153203480
	},
	{
		"code": 978,
		"buy": 34.15,
		"sell": 34.45,
		"time": 1609162803436
	},
	{
		"code": 978,
		"buy": 34.22,
		"sell": 34.55,
		"time": 1609226403148
	},
	{
		"code": 978,
		"buy": 34.22,
		"sell": 34.52,
		"time": 1609234204528
	},
	{
		"code": 978,
		"buy": 34.14,
		"sell": 34.49,
		"time": 1609244404555
	},
	{
		"code": 978,
		"buy": 34.21,
		"sell": 34.51,
		"time": 1609312805044
	},
	{
		"code": 978,
		"buy": 34.2,
		"sell": 34.55,
		"time": 1609316404033
	},
	{
		"code": 978,
		"buy": 34.27,
		"sell": 34.6,
		"time": 1609323603635
	},
	{
		"code": 978,
		"buy": 34.32,
		"sell": 34.62,
		"time": 1609327203859
	},
	{
		"code": 978,
		"buy": 34.35,
		"sell": 34.75,
		"time": 1609334405270
	},
	{
		"code": 978,
		"buy": 34.35,
		"sell": 34.8,
		"time": 1609399802944
	},
	{
		"code": 978,
		"buy": 34.38,
		"sell": 34.65,
		"time": 1609750203335
	},
	{
		"code": 978,
		"buy": 34.5,
		"sell": 34.9,
		"time": 1609753805407
	},
	{
		"code": 978,
		"buy": 34.55,
		"sell": 35,
		"time": 1609758006321
	},
	{
		"code": 978,
		"buy": 34.54,
		"sell": 35,
		"time": 1609770004994
	},
	{
		"code": 978,
		"buy": 34.49,
		"sell": 34.91,
		"time": 1609831203772
	},
	{
		"code": 978,
		"buy": 34.56,
		"sell": 34.97,
		"time": 1609834804473
	},
	{
		"code": 978,
		"buy": 34.5,
		"sell": 34.85,
		"time": 1609839607103
	},
	{
		"code": 978,
		"buy": 34.5,
		"sell": 34.75,
		"time": 1609842007745
	},
	{
		"code": 978,
		"buy": 34.45,
		"sell": 34.88,
		"time": 1609848007055
	},
	{
		"code": 978,
		"buy": 34.37,
		"sell": 34.75,
		"time": 1609850408844
	},
	{
		"code": 978,
		"buy": 34.33,
		"sell": 34.68,
		"time": 1609859406169
	},
	{
		"code": 978,
		"buy": 34.53,
		"sell": 34.97,
		"time": 1609917603284
	},
	{
		"code": 978,
		"buy": 34.47,
		"sell": 34.7,
		"time": 1609922403755
	},
	{
		"code": 978,
		"buy": 34.45,
		"sell": 34.73,
		"time": 1609924804940
	},
	{
		"code": 978,
		"buy": 34.52,
		"sell": 34.77,
		"time": 1609929005250
	},
	{
		"code": 978,
		"buy": 34.35,
		"sell": 34.75,
		"time": 1609944006005
	},
	{
		"code": 978,
		"buy": 34.15,
		"sell": 34.45,
		"time": 1610349004954
	},
	{
		"code": 978,
		"buy": 34.15,
		"sell": 34.4,
		"time": 1610359806344
	},
	{
		"code": 978,
		"buy": 34.1,
		"sell": 34.3,
		"time": 1610364604757
	},
	{
		"code": 978,
		"buy": 34,
		"sell": 34.25,
		"time": 1610374205680
	},
	{
		"code": 978,
		"buy": 34.05,
		"sell": 34.25,
		"time": 1610435409172
	},
	{
		"code": 978,
		"buy": 34,
		"sell": 34.2,
		"time": 1610438406171
	},
	{
		"code": 978,
		"buy": 33.97,
		"sell": 34.17,
		"time": 1610445006468
	},
	{
		"code": 978,
		"buy": 33.95,
		"sell": 34.12,
		"time": 1610449805265
	},
	{
		"code": 978,
		"buy": 34.02,
		"sell": 34.14,
		"time": 1610522403629
	},
	{
		"code": 978,
		"buy": 33.95,
		"sell": 34.15,
		"time": 1610527202714
	},
	{
		"code": 978,
		"buy": 33.9,
		"sell": 34.1,
		"time": 1610529003616
	},
	{
		"code": 978,
		"buy": 33.95,
		"sell": 34.1,
		"time": 1610548203661
	},
	{
		"code": 978,
		"buy": 33.94,
		"sell": 34.14,
		"time": 1610608802842
	},
	{
		"code": 978,
		"buy": 34,
		"sell": 34.2,
		"time": 1610617803281
	},
	{
		"code": 978,
		"buy": 33.9,
		"sell": 34.1,
		"time": 1610630404349
	},
	{
		"code": 978,
		"buy": 33.94,
		"sell": 34.14,
		"time": 1610707803928
	},
	{
		"code": 978,
		"buy": 33.9,
		"sell": 34.15,
		"time": 1610719811688
	},
	{
		"code": 978,
		"buy": 33.85,
		"sell": 34.15,
		"time": 1610781005248
	},
	{
		"code": 978,
		"buy": 33.85,
		"sell": 34.08,
		"time": 1610958605175
	},
	{
		"code": 978,
		"buy": 33.85,
		"sell": 34.1,
		"time": 1610965803891
	},
	{
		"code": 978,
		"buy": 33.9,
		"sell": 34.15,
		"time": 1610974202275
	},
	{
		"code": 978,
		"buy": 33.95,
		"sell": 34.25,
		"time": 1611040806038
	},
	{
		"code": 978,
		"buy": 33.95,
		"sell": 34.2,
		"time": 1611045004541
	},
	{
		"code": 978,
		"buy": 33.9,
		"sell": 34.15,
		"time": 1611048003842
	},
	{
		"code": 978,
		"buy": 33.95,
		"sell": 34.2,
		"time": 1611059405141
	},
	{
		"code": 978,
		"buy": 34,
		"sell": 34.25,
		"time": 1611067803342
	},
	{
		"code": 978,
		"buy": 34.02,
		"sell": 34.28,
		"time": 1611127203455
	},
	{
		"code": 978,
		"buy": 34.05,
		"sell": 34.25,
		"time": 1611134402260
	},
	{
		"code": 978,
		"buy": 34.1,
		"sell": 34.33,
		"time": 1611137402345
	},
	{
		"code": 978,
		"buy": 34.1,
		"sell": 34.3,
		"time": 1611145203101
	},
	{
		"code": 978,
		"buy": 34,
		"sell": 34.2,
		"time": 1611155407115
	},
	{
		"code": 978,
		"buy": 34.1,
		"sell": 34.35,
		"time": 1611213603471
	},
	{
		"code": 978,
		"buy": 34.05,
		"sell": 34.3,
		"time": 1611214204053
	},
	{
		"code": 978,
		"buy": 34.1,
		"sell": 34.3,
		"time": 1611224405342
	},
	{
		"code": 978,
		"buy": 34.15,
		"sell": 34.35,
		"time": 1611237606214
	},
	{
		"code": 978,
		"buy": 34.1,
		"sell": 34.3,
		"time": 1611304202405
	},
	{
		"code": 978,
		"buy": 34.08,
		"sell": 34.28,
		"time": 1611313202365
	},
	{
		"code": 978,
		"buy": 34.04,
		"sell": 34.3,
		"time": 1611559203750
	},
	{
		"code": 978,
		"buy": 34.15,
		"sell": 34.35,
		"time": 1611565206042
	},
	{
		"code": 978,
		"buy": 34.05,
		"sell": 34.25,
		"time": 1611567607871
	},
	{
		"code": 978,
		"buy": 34,
		"sell": 34.2,
		"time": 1611587407583
	},
	{
		"code": 978,
		"buy": 34.02,
		"sell": 34.2,
		"time": 1611665406362
	},
	{
		"code": 978,
		"buy": 34.05,
		"sell": 34.25,
		"time": 1611670806173
	}
]