[
	{
		"buy": 29.75,
		"sell": 30.3,
		"code": 978,
		"time": 1591770604538
	},
	{
		"buy": 28.85,
		"sell": 29.25,
		"code": 978,
		"time": 1590130203772
	},
	{
		"buy": 29.75,
		"sell": 29.75,
		"code": 978,
		"time": 1593151804652
	},
	{
		"buy": 29.8,
		"sell": 30.3,
		"code": 978,
		"time": 1593670803148
	},
	{
		"buy": 29.8,
		"sell": 30.05,
		"code": 978,
		"time": 1592892605316
	},
	{
		"buy": 29.7,
		"sell": 30,
		"code": 978,
		"time": 1591683604036
	},
	{
		"buy": 29,
		"sell": 29.45,
		"code": 978,
		"time": 1590474004635
	},
	{
		"buy": 29.15,
		"sell": 29.65,
		"code": 978,
		"time": 1590561004729
	},
	{
		"buy": 29.55,
		"sell": 30,
		"code": 978,
		"time": 1591165204121
	},
	{
		"buy": 29.8,
		"sell": 30.2,
		"code": 978,
		"time": 1592460606138
	},
	{
		"buy": 28.9,
		"sell": 29.3,
		"code": 978,
		"time": 1590042605596
	},
	{
		"buy": 28.85,
		"sell": 29.35,
		"code": 978,
		"time": 1590388802756
	},
	{
		"buy": 29.6,
		"sell": 29.95,
		"code": 978,
		"time": 1591251604369
	},
	{
		"buy": 29.7,
		"sell": 30.1,
		"code": 978,
		"time": 1592202604552
	},
	{
		"buy": 29.95,
		"sell": 30.6,
		"code": 978,
		"time": 1594016401996
	},
	{
		"buy": 29.85,
		"sell": 30.3,
		"code": 978,
		"time": 1592374202803
	},
	{
		"buy": 29.7,
		"sell": 29.9,
		"code": 978,
		"time": 1592806804965
	},
	{
		"buy": 29.5,
		"sell": 29.8,
		"code": 978,
		"time": 1591078805869
	},
	{
		"buy": 29.8,
		"sell": 30.1,
		"code": 978,
		"time": 1592979002581
	},
	{
		"buy": 29.7,
		"sell": 30.2,
		"code": 978,
		"time": 1591857004948
	},
	{
		"buy": 29.8,
		"sell": 30.05,
		"code": 978,
		"time": 1593065402941
	},
	{
		"buy": 28.7,
		"sell": 28.9,
		"code": 978,
		"time": 1589530804826
	},
	{
		"buy": 28.6,
		"sell": 28.85,
		"code": 978,
		"time": 1589783404215
	},
	{
		"buy": 28.85,
		"sell": 29.1,
		"code": 978,
		"time": 1589956802816
	},
	{
		"buy": 29.8,
		"sell": 30.05,
		"code": 978,
		"time": 1592547003618
	},
	{
		"buy": 29.7,
		"sell": 29.9,
		"code": 978,
		"time": 1593583803799
	},
	{
		"buy": 29.6,
		"sell": 29.95,
		"code": 978,
		"time": 1590993005089
	},
	{
		"buy": 29.7,
		"sell": 29.95,
		"code": 978,
		"time": 1593497402490
	},
	{
		"buy": 29.6,
		"sell": 29.9,
		"code": 978,
		"time": 1590734403241
	},
	{
		"buy": 29.9,
		"sell": 30.3,
		"code": 978,
		"time": 1591338603407
	},
	{
		"buy": 29.85,
		"sell": 30.2,
		"code": 978,
		"time": 1591942802727
	},
	{
		"buy": 29.8,
		"sell": 30.45,
		"code": 978,
		"time": 1592288405184
	},
	{
		"buy": 30.05,
		"sell": 30.7,
		"code": 978,
		"time": 1593757203424
	},
	{
		"buy": 31,
		"sell": 31.8,
		"code": 978,
		"time": 1595312404218
	},
	{
		"buy": 31.2,
		"sell": 32.2,
		"code": 978,
		"time": 1595412602553
	},
	{
		"buy": 31.7,
		"sell": 32.9,
		"code": 978,
		"time": 1596437402369
	},
	{
		"buy": 31.4,
		"sell": 32.75,
		"code": 978,
		"time": 1595831402353
	},
	{
		"buy": 32.2,
		"sell": 32.85,
		"code": 978,
		"time": 1597039802705
	},
	{
		"buy": 31.2,
		"sell": 32.85,
		"code": 978,
		"time": 1597299602998
	},
	{
		"buy": 32.3,
		"sell": 32.85,
		"code": 978,
		"time": 1597903202177
	},
	{
		"buy": 29.95,
		"sell": 30.4,
		"code": 978,
		"time": 1594362003749
	},
	{
		"buy": 29.95,
		"sell": 30.4,
		"code": 978,
		"time": 1594189202496
	},
	{
		"buy": 30.05,
		"sell": 30.7,
		"code": 978,
		"time": 1594621203268
	},
	{
		"buy": 30.85,
		"sell": 31.5,
		"code": 978,
		"time": 1595227203070
	},
	{
		"buy": 30.1,
		"sell": 30.7,
		"code": 978,
		"time": 1594275602805
	},
	{
		"buy": 30.65,
		"sell": 31.25,
		"code": 978,
		"time": 1594967402984
	},
	{
		"buy": 32.3,
		"sell": 33.05,
		"code": 978,
		"time": 1596694202497
	},
	{
		"buy": 30.4,
		"sell": 30.9,
		"code": 978,
		"time": 1594793404034
	},
	{
		"buy": 31.4,
		"sell": 32.65,
		"code": 978,
		"time": 1595916602946
	},
	{
		"buy": 30.55,
		"sell": 31.1,
		"code": 978,
		"time": 1594880402124
	},
	{
		"buy": 32.05,
		"sell": 32.45,
		"code": 978,
		"time": 1598422202628
	},
	{
		"buy": 32.2,
		"sell": 32.85,
		"code": 978,
		"time": 1597302002827
	},
	{
		"buy": 30.2,
		"sell": 30.8,
		"code": 978,
		"time": 1594707002533
	},
	{
		"buy": 32.3,
		"sell": 33.15,
		"code": 978,
		"time": 1596782402614
	},
	{
		"buy": 32.1,
		"sell": 32.55,
		"code": 978,
		"time": 1598336402477
	},
	{
		"buy": 32,
		"sell": 32.9,
		"code": 978,
		"time": 1596609002530
	},
	{
		"buy": 31.3,
		"sell": 32.35,
		"code": 978,
		"time": 1595571602413
	},
	{
		"buy": 31.3,
		"sell": 32.5,
		"code": 978,
		"time": 1595485201774
	},
	{
		"buy": 31.45,
		"sell": 32.75,
		"code": 978,
		"time": 1596004202106
	},
	{
		"buy": 32.3,
		"sell": 32.8,
		"code": 978,
		"time": 1597990203002
	},
	{
		"buy": 29.95,
		"sell": 30.45,
		"code": 978,
		"time": 1594102202760
	},
	{
		"buy": 32,
		"sell": 32.95,
		"code": 978,
		"time": 1596521402418
	},
	{
		"buy": 32.05,
		"sell": 32.6,
		"code": 978,
		"time": 1598508602624
	},
	{
		"buy": 32.15,
		"sell": 32.75,
		"code": 978,
		"time": 1598595002422
	},
	{
		"buy": 32.45,
		"sell": 32.95,
		"code": 978,
		"time": 1598854202544
	},
	{
		"buy": 32.5,
		"sell": 33.2,
		"code": 978,
		"time": 1598941202812
	},
	{
		"buy": 32.4,
		"sell": 33.2,
		"code": 978,
		"time": 1599027002516
	},
	{
		"buy": 32.4,
		"sell": 32.8,
		"code": 978,
		"time": 1599113402568
	},
	{
		"buy": 32.45,
		"sell": 32.9,
		"code": 978,
		"time": 1599199802537
	},
	{
		"buy": 32.5,
		"sell": 32.95,
		"code": 978,
		"time": 1599459003076
	},
	{
		"buy": 32.5,
		"sell": 32.9,
		"code": 978,
		"time": 1599543602006
	},
	{
		"buy": 32.6,
		"sell": 33.05,
		"code": 978,
		"time": 1599718203274
	},
	{
		"buy": 32.8,
		"sell": 33.2,
		"code": 978,
		"time": 1599804601974
	},
	{
		"buy": 32.8,
		"sell": 33.3,
		"code": 978,
		"time": 1600063803785
	},
	{
		"buy": 32.5,
		"sell": 33.45,
		"code": 978,
		"time": 1600150801953
	},
	{
		"buy": 32.55,
		"sell": 33.5,
		"code": 978,
		"time": 1600237206244
	},
	{
		"buy": 32.55,
		"sell": 33.2,
		"code": 978,
		"time": 1600324802563
	},
	{
		"buy": 32.55,
		"sell": 33.45,
		"code": 978,
		"time": 1600409403109
	},
	{
		"buy": 32.65,
		"sell": 33.65,
		"code": 978,
		"time": 1600670402149
	},
	{
		"buy": 32.65,
		"sell": 33.35,
		"code": 978,
		"time": 1600756802445
	},
	{
		"buy": 32.7,
		"sell": 33.15,
		"code": 978,
		"time": 1600842602218
	},
	{
		"buy": 32.7,
		"sell": 33.1,
		"code": 978,
		"time": 1601014802299
	},
	{
		"buy": 32.75,
		"sell": 33.1,
		"code": 978,
		"time": 1601274002266
	},
	{
		"buy": 32.75,
		"sell": 33.35,
		"code": 978,
		"time": 1601447403836
	},
	{
		"buy": 32.78,
		"sell": 33.35,
		"code": 978,
		"time": 1601619002193
	},
	{
		"buy": 32.8,
		"sell": 33.45,
		"code": 978,
		"time": 1601878802660
	},
	{
		"buy": 32.8,
		"sell": 33.6,
		"code": 978,
		"time": 1601966404625
	},
	{
		"buy": 32.85,
		"sell": 33.45,
		"code": 978,
		"time": 1602051002343
	},
	{
		"buy": 32.85,
		"sell": 33.3,
		"code": 978,
		"time": 1602224402446
	},
	{
		"buy": 32.9,
		"sell": 33.45,
		"code": 978,
		"time": 1602483602719
	},
	{
		"buy": 32.9,
		"sell": 33.3,
		"code": 978,
		"time": 1602829202457
	},
	{
		"buy": 32.9,
		"sell": 33.35,
		"code": 978,
		"time": 1603089003202
	},
	{
		"buy": 33,
		"sell": 33.6,
		"code": 978,
		"time": 1603174204448
	},
	{
		"buy": 33,
		"sell": 33.7,
		"code": 978,
		"time": 1603261804171
	},
	{
		"buy": 33,
		"sell": 33.6,
		"code": 978,
		"time": 1603348802712
	},
	{
		"buy": 33.05,
		"sell": 33.6,
		"code": 978,
		"time": 1603782602430
	},
	{
		"buy": 33.05,
		"sell": 33.55,
		"code": 978,
		"time": 1603956602761
	},
	{
		"buy": 33.05,
		"sell": 33.45,
		"code": 978,
		"time": 1604041802672
	},
	{
		"buy": 33.05,
		"sell": 33.55,
		"code": 978,
		"time": 1604389802264
	},
	{
		"buy": 33.05,
		"sell": 33.5,
		"code": 978,
		"time": 1605511203101
	},
	{
		"buy": 33.05,
		"sell": 33.55,
		"code": 978,
		"time": 1605772801919
	},
	{
		"buy": 33.1,
		"sell": 33.85,
		"code": 978,
		"time": 1605857402794
	},
	{
		"buy": 33.1,
		"sell": 33.75,
		"code": 978,
		"time": 1606116003159
	},
	{
		"buy": 33.1,
		"sell": 33.85,
		"code": 978,
		"time": 1606288802920
	},
	{
		"buy": 33.15,
		"sell": 34.05,
		"code": 978,
		"time": 1606374602767
	},
	{
		"buy": 33.15,
		"sell": 34.15,
		"code": 978,
		"time": 1606462803765
	},
	{
		"buy": 33.2,
		"sell": 34.35,
		"code": 978,
		"time": 1606722002750
	},
	{
		"buy": 33.2,
		"sell": 34.2,
		"code": 978,
		"time": 1606807803928
	},
	{
		"buy": 33.2,
		"sell": 34.5,
		"code": 978,
		"time": 1606911602824
	},
	{
		"buy": 33.2,
		"sell": 34.4,
		"code": 978,
		"time": 1606980019397
	},
	{
		"buy": 33.25,
		"sell": 34.45,
		"code": 978,
		"time": 1607068804769
	},
	{
		"buy": 33.25,
		"sell": 34.5,
		"code": 978,
		"time": 1607327402333
	},
	{
		"buy": 33.25,
		"sell": 34.4,
		"code": 978,
		"time": 1607412602344
	},
	{
		"buy": 33.3,
		"sell": 34.4,
		"code": 978,
		"time": 1607498402433
	},
	{
		"buy": 33.3,
		"sell": 34.2,
		"code": 978,
		"time": 1607584802612
	},
	{
		"buy": 33.3,
		"sell": 34.1,
		"code": 978,
		"time": 1607930403717
	},
	{
		"buy": 33.3,
		"sell": 33.95,
		"code": 978,
		"time": 1608016803029
	},
	{
		"buy": 33.35,
		"sell": 33.95,
		"code": 978,
		"time": 1608103202882
	},
	{
		"buy": 33.4,
		"sell": 34.2,
		"code": 978,
		"time": 1608189003055
	},
	{
		"buy": 33.4,
		"sell": 34.4,
		"code": 978,
		"time": 1608275402239
	},
	{
		"buy": 33.45,
		"sell": 34.6,
		"code": 978,
		"time": 1608622203909
	},
	{
		"buy": 33.5,
		"sell": 34.9,
		"code": 978,
		"time": 1608709202737
	},
	{
		"buy": 33.5,
		"sell": 34.8,
		"code": 978,
		"time": 1608796202543
	},
	{
		"buy": 34.55,
		"sell": 35,
		"code": 978,
		"time": 1609398602648
	},
	{
		"buy": 33.55,
		"sell": 35,
		"code": 978,
		"time": 1609401003612
	},
	{
		"buy": 33.6,
		"sell": 35.05,
		"code": 978,
		"time": 1609754404075
	},
	{
		"buy": 33.65,
		"sell": 35.15,
		"code": 978,
		"time": 1609837205757
	},
	{
		"buy": 33.7,
		"sell": 34.95,
		"code": 978,
		"time": 1609918203663
	},
	{
		"buy": 33.75,
		"sell": 34.5,
		"code": 978,
		"time": 1610436606780
	},
	{
		"buy": 33.8,
		"sell": 34.4,
		"code": 978,
		"time": 1610523006533
	},
	{
		"buy": 33.8,
		"sell": 34.3,
		"code": 978,
		"time": 1610609403274
	},
	{
		"buy": 33.8,
		"sell": 34.35,
		"code": 978,
		"time": 1610781604519
	},
	{
		"buy": 33.8,
		"sell": 34.25,
		"code": 978,
		"time": 1610955005383
	},
	{
		"buy": 33.85,
		"sell": 34.35,
		"code": 978,
		"time": 1611043205053
	},
	{
		"buy": 33.85,
		"sell": 34.25,
		"code": 978,
		"time": 1611127204285
	},
	{
		"buy": 33.85,
		"sell": 34.4,
		"code": 978,
		"time": 1611213603319
	},
	{
		"buy": 33.85,
		"sell": 34.45,
		"code": 978,
		"time": 1611300003059
	},
	{
		"buy": 33.85,
		"sell": 34.25,
		"code": 978,
		"time": 1611646202957
	},
	{
		"buy": 33.85,
		"sell": 34.35,
		"code": 978,
		"time": 1611732002339
	},
	{
		"buy": 33.85,
		"sell": 34.2,
		"code": 978,
		"time": 1611818402136
	},
	{
		"buy": 33.9,
		"sell": 34.2,
		"code": 978,
		"time": 1612163402446
	},
	{
		"buy": 33.75,
		"sell": 33.95,
		"code": 978,
		"time": 1612251005250
	},
	{
		"buy": 33.65,
		"sell": 33.85,
		"code": 978,
		"time": 1612338003034
	},
	{
		"buy": 33.45,
		"sell": 33.65,
		"code": 978,
		"time": 1612423203445
	},
	{
		"buy": 33.15,
		"sell": 33.4,
		"code": 978,
		"time": 1612509604887
	},
	{
		"buy": 33.2,
		"sell": 33.4,
		"code": 978,
		"time": 1612773603559
	},
	{
		"buy": 33.25,
		"sell": 33.45,
		"code": 978,
		"time": 1612855205543
	},
	{
		"buy": 33.4,
		"sell": 33.7,
		"code": 978,
		"time": 1612941602496
	},
	{
		"buy": 33.65,
		"sell": 34.1,
		"code": 978,
		"time": 1613028003935
	},
	{
		"buy": 33.55,
		"sell": 33.7,
		"code": 978,
		"time": 1613114403077
	},
	{
		"buy": 33.65,
		"sell": 34.05,
		"code": 978,
		"time": 1613373603082
	},
	{
		"buy": 33.6,
		"sell": 33.9,
		"code": 978,
		"time": 1613460004187
	},
	{
		"buy": 33.55,
		"sell": 33.85,
		"code": 978,
		"time": 1613546402812
	},
	{
		"buy": 33.3,
		"sell": 33.6,
		"code": 978,
		"time": 1613632802881
	},
	{
		"buy": 33.5,
		"sell": 33.8,
		"code": 978,
		"time": 1613727604700
	},
	{
		"buy": 33.6,
		"sell": 33.9,
		"code": 978,
		"time": 1613979005306
	},
	{
		"buy": 33.65,
		"sell": 34.05,
		"code": 978,
		"time": 1614066002722
	},
	{
		"buy": 33.7,
		"sell": 34.05,
		"code": 978,
		"time": 1614151804154
	},
	{
		"buy": 33.85,
		"sell": 34.15,
		"code": 978,
		"time": 1614238803275
	},
	{
		"buy": 33.7,
		"sell": 33.9,
		"code": 978,
		"time": 1614583803374
	},
	{
		"buy": 33.5,
		"sell": 33.7,
		"code": 978,
		"time": 1614670203072
	},
	{
		"buy": 33.5,
		"sell": 33.75,
		"code": 978,
		"time": 1614756602959
	},
	{
		"buy": 33.3,
		"sell": 33.6,
		"code": 978,
		"time": 1614843004025
	},
	{
		"buy": 32.9,
		"sell": 33.3,
		"code": 978,
		"time": 1614928802728
	},
	{
		"buy": 32.85,
		"sell": 33.3,
		"code": 978,
		"time": 1615274405136
	},
	{
		"buy": 32.8,
		"sell": 33.05,
		"code": 978,
		"time": 1615361403148
	},
	{
		"buy": 32.85,
		"sell": 33.15,
		"code": 978,
		"time": 1615447803025
	},
	{
		"buy": 32.95,
		"sell": 33.2,
		"code": 978,
		"time": 1615534203321
	},
	{
		"buy": 32.95,
		"sell": 33.17,
		"code": 978,
		"time": 1615792805422
	},
	{
		"buy": 32.75,
		"sell": 33.05,
		"code": 978,
		"time": 1615879202901
	},
	{
		"buy": 32.85,
		"sell": 33.15,
		"code": 978,
		"time": 1615965606105
	},
	{
		"buy": 32.95,
		"sell": 33.3,
		"code": 978,
		"time": 1616052604229
	},
	{
		"buy": 32.85,
		"sell": 33.1,
		"code": 978,
		"time": 1616139004010
	},
	{
		"buy": 32.75,
		"sell": 33,
		"code": 978,
		"time": 1616398804313
	},
	{
		"buy": 32.8,
		"sell": 33.05,
		"code": 978,
		"time": 1616485802469
	},
	{
		"buy": 32.75,
		"sell": 33.05,
		"code": 978,
		"time": 1616570402826
	},
	{
		"buy": 32.85,
		"sell": 33.1,
		"code": 978,
		"time": 1616656203472
	},
	{
		"buy": 32.75,
		"sell": 33.05,
		"code": 978,
		"time": 1616999403352
	},
	{
		"buy": 32.75,
		"sell": 32.95,
		"code": 978,
		"time": 1617085803186
	},
	{
		"buy": 31.95,
		"sell": 34.25,
		"code": 978,
		"time": 1655886605351
	},
	{
		"buy": 31.95,
		"sell": 34.55,
		"code": 978,
		"time": 1656569402738
	},
	{
		"buy": 31.45,
		"sell": 34.05,
		"code": 978,
		"time": 1657088402789
	},
	{
		"buy": 30.95,
		"sell": 33.25,
		"code": 978,
		"time": 1657693203172
	},
	{
		"buy": 30.95,
		"sell": 32.65,
		"code": 978,
		"time": 1658125203069
	},
	{
		"buy": 36.52,
		"sell": 37.55,
		"code": 978,
		"time": 1658394604058
	},
	{
		"buy": 37.22,
		"sell": 37.85,
		"code": 978,
		"time": 1658472002924
	},
	{
		"buy": 37.4,
		"sell": 37.95,
		"code": 978,
		"time": 1658887804468
	},
	{
		"buy": 37.01,
		"sell": 37.65,
		"code": 978,
		"time": 1658902803382
	},
	{
		"buy": 37.1,
		"sell": 37.75,
		"code": 978,
		"time": 1658989203192
	},
	{
		"buy": 37.3,
		"sell": 37.85,
		"code": 978,
		"time": 1659334803812
	},
	{
		"buy": 37.35,
		"sell": 38.04,
		"code": 978,
		"time": 1659507603434
	},
	{
		"buy": 37.2,
		"sell": 37.85,
		"code": 978,
		"time": 1659594003914
	},
	{
		"buy": 37.05,
		"sell": 38.15,
		"code": 978,
		"time": 1659680403941
	},
	{
		"buy": 37.22,
		"sell": 38.15,
		"code": 978,
		"time": 1659939604877
	},
	{
		"buy": 37.15,
		"sell": 38.15,
		"code": 978,
		"time": 1660025403986
	},
	{
		"buy": 37.2,
		"sell": 38.15,
		"code": 978,
		"time": 1660111803974
	},
	{
		"buy": 37.45,
		"sell": 38.4,
		"code": 978,
		"time": 1660198803879
	},
	{
		"buy": 37.6,
		"sell": 38.5,
		"code": 978,
		"time": 1660285204330
	},
	{
		"buy": 37.3,
		"sell": 38.5,
		"code": 978,
		"time": 1660544403023
	},
	{
		"buy": 37.1,
		"sell": 38.5,
		"code": 978,
		"time": 1660630802745
	},
	{
		"buy": 37.02,
		"sell": 38.3,
		"code": 978,
		"time": 1660890003616
	},
	{
		"buy": 36.55,
		"sell": 38,
		"code": 978,
		"time": 1661148602610
	},
	{
		"buy": 36.37,
		"sell": 37.6,
		"code": 978,
		"time": 1661334604507
	},
	{
		"buy": 36.37,
		"sell": 37.4,
		"code": 978,
		"time": 1661421003108
	}
]