[
	{
		"buy": 35.95,
		"sell": 45.5,
		"code": 826,
		"time": 1655886605346
	},
	{
		"buy": 35.8,
		"sell": 45.5,
		"code": 826,
		"time": 1656051004537
	},
	{
		"buy": 35.95,
		"sell": 45.5,
		"code": 826,
		"time": 1656310202920
	},
	{
		"buy": 35.6,
		"sell": 45.5,
		"code": 826,
		"time": 1656569402736
	},
	{
		"buy": 35.5,
		"sell": 45.5,
		"code": 826,
		"time": 1656655802699
	},
	{
		"buy": 35.6,
		"sell": 45.5,
		"code": 826,
		"time": 1657001403759
	},
	{
		"buy": 35.16,
		"sell": 45.5,
		"code": 826,
		"time": 1657087802336
	},
	{
		"buy": 34.88,
		"sell": 45.2,
		"code": 826,
		"time": 1657174204222
	},
	{
		"buy": 35.1,
		"sell": 45.5,
		"code": 826,
		"time": 1657260602659
	},
	{
		"buy": 35.15,
		"sell": 45.58,
		"code": 826,
		"time": 1657519804790
	},
	{
		"buy": 35,
		"sell": 45.3,
		"code": 826,
		"time": 1657606202858
	},
	{
		"buy": 34.74,
		"sell": 45,
		"code": 826,
		"time": 1657692603314
	}
]